Workbook

Sheet Read Me
B2: TCS — Five-Year Scenario Model (FY27–FY31)
B3: Prepared for the Chairman, Tata Sons · base year FY26 (year ended 31 March 2026)
B6: WHAT THIS IS | C6: A driver-based model of TCS revenue, margin, cash and dividend under four scenarios, and what each means for Tata Sons' parent-level funding capacity.
B7: HOW TO USE IT | C7: Every blue cell is an input you can change. Everything black is a formula. Change an assumption on 'Assumptions' and every sheet recalculates.
B9: COLOUR LEGEND
B10: Blue text | C10: Hard-coded input / scenario lever — edit these.
B11: Black text | C11: Formula — do not overwrite.
B12: Green text | C12: Link to another sheet in this workbook.
B13: Yellow fill | C13: Key judgement call. These drive the answer; challenge them first.
B15: SHEETS
B16: History | C16: TCS actuals FY22–FY26 and Q1 FY27, with sources.
B17: Assumptions | C17: All shared parameters, the revenue decomposition, and the four scenario driver blocks.
B18: Revenue Build | C18: Bucket-level revenue build for each scenario, FY27–FY31.
B19: Scenario Output | C19: Full P&L, cash, dividend and headcount output for each scenario.
B20: Tata Sons Bridge | C20: Parent-level cash bridge: TCS dividend vs. the capital call from Air India, Tata Electronics, Agratas and Tata Digital.
B21: Sensitivity | C21: FY31 dividend to Tata Sons across revenue CAGR × terminal operating margin.
B22: Risk Register | C22: Revenue-at-risk by exposure bucket.
B24: THE ONE CAVEAT | C24: TCS stopped disclosing a service-line revenue split after FY21. The seven-bucket decomposition on 'Assumptions' is a reconstruction, not a disclosure. It is the single most challengeable input in this model and the first thing to replace with internal MIS.
B26: PRIMARY SOURCES | C26: TCS Q4 FY26 Fact Sheet and press release; TCS Q1 FY27 press release; Tata Sons FY26 accounts as reported; Business Standard; Business Today; company filings.

Sheet History
A1: TCS — Reported actuals
A2: Source: TCS quarterly fact sheets and results press releases, tcs.com/investor-relations
A4: Metric | B4: FY22 | C4: FY23 | D4: FY24 | E4: FY25 | F4: FY26 | G4: Q1 FY27
A5: Revenue ($mn) | B5: 25707 | C5: 27927 | D5: 29080 | E5: 30180 | F5: 30017 | G5: 7624
A6: Revenue growth, reported USD | B6: 0.157 | C6: 0.086 | D6: 0.041 | E6: 0.038 | F6: -0.005
A7: Revenue growth, constant currency | B7: 0.157 | C7: 0.138 | D7: 0.034 | E7: 0.042 | F7: -0.024 | G7: 0.032
A8: Operating margin | B8: 0.25 | C8: 0.244 | D8: 0.246 | E8: 0.243 | F8: 0.25 | G8: 0.24
A9: Net margin | B9: 0.204 | C9: 0.192 | D9: 0.196 | E9: 0.19 | F9: 0.198 | G9: 0.192
A10: Net income ($mn) | B10: 5240 | C10: 5364 | D10: 5697 | E10: 5739 | F10: 5938 | G10: 1460
A11: Revenue (₹ crore) | B11: 191754 | C11: 225458 | D11: 240893 | E11: 255324 | F11: 267021
A12: Net income (₹ crore) | B12: 38449 | C12: 42303 | D12: 46099 | E12: 48797 | F12: 49454
A13: Order book / TCV ($bn) | B13: 34.6 | C13: 34.1 | D13: 42.7 | E13: 39.4 | F13: 40.7 | G13: 9.5
A14: Closing headcount | B14: 592195 | C14: 614795 | D14: 601546 | E14: 607979 | F14: 584519 | G14: 593798
A15: Dividend per share (₹) | B15: 43 | C15: 115 | D15: 73 | E15: 126 | F15: 110 | G15: 12
A16: Total shareholder payout (₹ crore) | B16: 15671 | C16: 42084 | D16: 26411 | E16: 44962 | F16: 39571
A18: Derived
A19: Revenue per employee ($) | B19: =B5*1000000/B14 -> 43409.688 | C19: =C5*1000000/C14 -> 45424.898 | D19: =D5*1000000/D14 -> 48342.105 | E19: =E5*1000000/E14 -> 49639.872 | F19: =F5*1000000/F14 -> 51353.335
A20: Implied ₹/US$ (revenue-weighted) | B20: =B11*10/B5 -> 74.592134 | C20: =C11*10/C5 -> 80.731192 | D20: =D11*10/D5 -> 82.838033 | E20: =E11*10/E5 -> 84.600398 | F20: =F11*10/F5 -> 88.956591
A21: Payout as % of net income | B21: =B16/B12 -> 0.40757887 | C21: =C16/C12 -> 0.99482306 | D21: =D16/D12 -> 0.57291915 | E21: =E16/E12 -> 0.9214091 | F21: =F16/F12 -> 0.80015772
A23: Note: FY26 was the first US-dollar revenue decline in TCS's listed history (-0.5% reported, -2.4% constant currency).

Sheet Assumptions
A1: Assumptions and scenario drivers
A2: Blue = input. Yellow = key judgement. Change these and the whole model moves.
A4: 1. Shared parameters
A5: FY26 revenue ($mn) [actual] | B5: 30017 | J5: TCS Q4 FY26 press release
A6: FY26 closing headcount [actual] | B6: 584519 | J6: TCS Q4 FY26 fact sheet
A7: FY26 revenue per employee ($) | B7: 51353 | J7: Derived
A8: FY26 implied ₹/US$ | B8: 88.96 | J8: ₹2,67,021 cr / $30,017mn
A9: ₹ depreciation p.a. | B9: 0.02 | J9: Long-run inflation differential
A10: Other income as % of revenue | B10: 0.016 | J10: Treasury income on ~₹50,000 cr cash
A11: Effective tax rate | B11: 0.255 | J11: FY26 effective rate
A12: Tata Sons stake in TCS | B12: 0.7174 | J12: 2,59,54,99,419 shares = 71.74%
A13: TCS shares outstanding (crore) | B13: 361.8 | J13: For DPS calculation
A15: 2. Revenue decomposition by AI exposure (FY26 base)
A16: Exposure bucket | B16: FY26 weight | C16: FY26 $mn | D16: Automatable share | E16: Gross rev at risk $mn | F16: Volume decay p.a.
A17: Application Development & Maintenance (custom) | B17: 0.32 | C17: =B17*$B$5 -> 9605.44 | D17: 0.55 | E17: =C17*D17 -> 5282.992 | F17: 1 | J17: Code generation, test automation and agentic L1/L2 support attack the core of this book. Largest single pool and the most exposed.
A18: Enterprise / Package Application Services | B18: 0.13 | C18: =B18*$B$5 -> 3902.21 | D18: 0.4 | E18: =C18*D18 -> 1560.884 | F18: 1 | J18: SAP/Oracle/Salesforce migration and rollout. Config work automates; change management, data migration and integration hold value.
A19: Cloud & Infrastructure Managed Services | B19: 0.16 | C19: =B19*$B$5 -> 4802.72 | D19: 0.5 | E19: =C19*D19 -> 2401.36 | F19: 1 | J19: AIOps compresses run-cost; offset by AI-infrastructure build, GPU estate operations and the HyperVault adjacency.
A20: Business Process Services | B20: 0.1 | C20: =B20*$B$5 -> 3001.7 | D20: 0.65 | E20: =C20*D20 -> 1951.105 | F20: 1 | J20: Most directly substitutable. Agentic workflows displace seat-based delivery; the FTE pricing model is the liability.
A21: Engineering & R&D Services | B21: 0.09 | C21: =B21*$B$5 -> 2701.53 | D21: 0.25 | E21: =C21*D21 -> 675.3825 | F21: 1 | J21: Embedded, semiconductor, automotive software. Least substitutable near-term and structurally growing.
A22: Consulting, Data, AI & Cybersecurity | B22: 0.15 | C22: =B22*$B$5 -> 4502.55 | D22: 0.15 | E22: =C22*D22 -> 675.3825 | F22: 0.88 | J22: The growth engine. AI-native demand, data estate rebuild, model governance, security. TCS AI book already ~8.5% of revenue.
A23: Products & Platforms (BaNCS, ignio, iON, ADD) | B23: 0.05 | C23: =B23*$B$5 -> 1500.85 | D23: 0.1 | E23: =C23*D23 -> 150.085 | F23: 0.92 | J23: IP-led, non-linear. AI raises product value rather than deflating it. Strategically under-scaled at ~5% of revenue.
A24: Total | B24: =SUM(B17:B23) -> 1 | C24: =SUM(C17:C23) -> 30017 | E24: =SUM(E17:E23) -> 12697.191
A25: TCS has not disclosed a service-line revenue split since FY21. Weights are a reconstruction from the last disclosure, deal mix and peer structure — replace with internal MIS.
A28: 3. Scenario drivers — Bull — AI Dividend | H28: Probability | I28: 0.15
A29: Per-bucket annual drivers | B29: Realisation deflation | C29: Volume growth
A30: Application Development & Maintenance (custom) | B30: -0.05 | C30: 0.09
A31: Enterprise / Package Application Services | B31: -0.03 | C31: 0.1
A32: Cloud & Infrastructure Managed Services | B32: -0.04 | C32: 0.12
A33: Business Process Services | B33: -0.06 | C33: 0.1
A34: Engineering & R&D Services | B34: -0.01 | C34: 0.12
A35: Consulting, Data, AI & Cybersecurity | B35: 0 | C35: 0.26
A36: Products & Platforms (BaNCS, ignio, iON, ADD) | B36: 0 | C36: 0.16
A37: Year-specific parameters | B37: FY27 | C37: FY28 | D37: FY29 | E37: FY30 | F37: FY31
A38: Deflation phasing multiplier | B38: 1 | C38: 1 | D38: 0.9 | E38: 0.9 | F38: 0.8
A39: Operating margin | B39: 0.245 | C39: 0.255 | D39: 0.262 | E39: 0.267 | F39: 0.27
A40: Free cash flow / net income | B40: 0.8 | C40: 0.75 | D40: 0.79 | E40: 0.84 | F40: 0.88
A41: Dividend as % of free cash flow | B41: 0.92 | C41: 0.92 | D41: 0.92 | E41: 0.92 | F41: 0.92
A42: Revenue per employee growth p.a. | B42: 0.055
A45: 3. Scenario drivers — Base — Managed Transition | H45: Probability | I45: 0.4
A46: Per-bucket annual drivers | B46: Realisation deflation | C46: Volume growth
A47: Application Development & Maintenance (custom) | B47: -0.06 | C47: 0.06
A48: Enterprise / Package Application Services | B48: -0.04 | C48: 0.07
A49: Cloud & Infrastructure Managed Services | B49: -0.05 | C49: 0.08
A50: Business Process Services | B50: -0.08 | C50: 0.06
A51: Engineering & R&D Services | B51: -0.02 | C51: 0.08
A52: Consulting, Data, AI & Cybersecurity | B52: -0.02 | C52: 0.18
A53: Products & Platforms (BaNCS, ignio, iON, ADD) | B53: -0.01 | C53: 0.11
A54: Year-specific parameters | B54: FY27 | C54: FY28 | D54: FY29 | E54: FY30 | F54: FY31
A55: Deflation phasing multiplier | B55: 1 | C55: 1 | D55: 1 | E55: 0.9 | F55: 0.9
A56: Operating margin | B56: 0.243 | C56: 0.246 | D56: 0.25 | E56: 0.252 | F56: 0.255
A57: Free cash flow / net income | B57: 0.8 | C57: 0.76 | D57: 0.78 | E57: 0.82 | F57: 0.85
A58: Dividend as % of free cash flow | B58: 0.93 | C58: 0.93 | D58: 0.92 | E58: 0.92 | F58: 0.92
A59: Revenue per employee growth p.a. | B59: 0.04
A62: 3. Scenario drivers — Bear — Slow Bleed | H62: Probability | I62: 0.3
A63: Per-bucket annual drivers | B63: Realisation deflation | C63: Volume growth
A64: Application Development & Maintenance (custom) | B64: -0.09 | C64: 0.02
A65: Enterprise / Package Application Services | B65: -0.06 | C65: 0.03
A66: Cloud & Infrastructure Managed Services | B66: -0.08 | C66: 0.04
A67: Business Process Services | B67: -0.12 | C67: 0.02
A68: Engineering & R&D Services | B68: -0.04 | C68: 0.04
A69: Consulting, Data, AI & Cybersecurity | B69: -0.04 | C69: 0.11
A70: Products & Platforms (BaNCS, ignio, iON, ADD) | B70: -0.03 | C70: 0.06
A71: Year-specific parameters | B71: FY27 | C71: FY28 | D71: FY29 | E71: FY30 | F71: FY31
A72: Deflation phasing multiplier | B72: 0.8 | C72: 1 | D72: 1.1 | E72: 1 | F72: 0.9
A73: Operating margin | B73: 0.24 | C73: 0.234 | D73: 0.228 | E73: 0.224 | F73: 0.22
A74: Free cash flow / net income | B74: 0.78 | C74: 0.72 | D74: 0.74 | E74: 0.78 | F74: 0.82
A75: Dividend as % of free cash flow | B75: 0.95 | C75: 0.93 | D75: 0.91 | E75: 0.9 | F75: 0.9
A76: Revenue per employee growth p.a. | B76: 0.03
A79: 3. Scenario drivers — Severe — Structural Break | H79: Probability | I79: 0.15
A80: Per-bucket annual drivers | B80: Realisation deflation | C80: Volume growth
A81: Application Development & Maintenance (custom) | B81: -0.13 | C81: 0
A82: Enterprise / Package Application Services | B82: -0.09 | C82: 0
A83: Cloud & Infrastructure Managed Services | B83: -0.11 | C83: 0.01
A84: Business Process Services | B84: -0.18 | C84: -0.02
A85: Engineering & R&D Services | B85: -0.06 | C85: 0.01
A86: Consulting, Data, AI & Cybersecurity | B86: -0.07 | C86: 0.05
A87: Products & Platforms (BaNCS, ignio, iON, ADD) | B87: -0.06 | C87: 0.02
A88: Year-specific parameters | B88: FY27 | C88: FY28 | D88: FY29 | E88: FY30 | F88: FY31
A89: Deflation phasing multiplier | B89: 0.6 | C89: 1 | D89: 1.2 | E89: 1.1 | F89: 0.9
A90: Operating margin | B90: 0.235 | C90: 0.22 | D90: 0.202 | E90: 0.188 | F90: 0.175
A91: Free cash flow / net income | B91: 0.75 | C91: 0.66 | D91: 0.68 | E91: 0.74 | F91: 0.8
A92: Dividend as % of free cash flow | B92: 0.95 | C92: 0.9 | D92: 0.85 | E92: 0.85 | F92: 0.85
A93: Revenue per employee growth p.a. | B93: 0.015
A96: 4. Tata Sons parent-level assumptions (₹ crore)
A97: Non-TCS dividend income, FY26 [actual] | B97: 4237 | J97: Total FY26 dividend income ₹32,528 cr less TCS ₹28,291 cr
A98: Non-TCS dividend growth p.a. | B98: 0.09 | J98: Tata Motors, Tata Steel, Titan, Tata Power, TCPL, IHCL
A99: Parent opex, interest and tax, FY26 | B99: 6984 | J99: Dividend income less reported operating cash flow of ₹25,544 cr
A100: Parent cost growth p.a. | B100: 0.06
A101: Opening net cash, FY26 [actual] | B101: 21841 | J101: No borrowings at FY26 close
A103: Equity deployment into strategic bets (₹ crore) | B103: FY27 | C103: FY28 | D103: FY29 | E103: FY30 | F103: FY31
A104: Air India, Tata Electronics, Agratas, Tata Digital | B104: 20000 | C104: 24000 | D104: 26000 | E104: 27000 | F104: 28000
A105: FY26 actual deployment was ₹15,956 cr (₹15,089 cr subsidiaries + ₹867 cr associates/JVs). Forward path reflects the Dholera fab (₹91,000 cr), Assam ATMP (₹27,000 cr), Air India fleet and Agratas. Held constant across scenarios by design — the commitments do not shrink because TCS slows.

Sheet Revenue Build
A1: Revenue build by exposure bucket ($mn)
A2: Each year = prior year × (1 + volume growth × decay^n) × (1 + deflation × phasing)
A4: Bull — AI Dividend
A5: Exposure bucket | B5: FY26 | C5: FY27 | D5: FY28 | E5: FY29 | F5: FY30 | G5: FY31
A6: Application Development & Maintenance (custom) | B6: =Assumptions!C17 -> 9605.44 | C6: =B6*(1+Assumptions!$C$30*Assumptions!$F$17^0)*(1+Assumptions!$B$30*Assumptions!B$38) -> 9946.4331 | D6: =C6*(1+Assumptions!$C$30*Assumptions!$F$17^1)*(1+Assumptions!$B$30*Assumptions!C$38) -> 10299.531 | E6: =D6*(1+Assumptions!$C$30*Assumptions!$F$17^2)*(1+Assumptions!$B$30*Assumptions!D$38) -> 10721.297 | F6: =E6*(1+Assumptions!$C$30*Assumptions!$F$17^3)*(1+Assumptions!$B$30*Assumptions!E$38) -> 11160.334 | G6: =F6*(1+Assumptions!$C$30*Assumptions!$F$17^4)*(1+Assumptions!$B$30*Assumptions!F$38) -> 11678.174
A7: Enterprise / Package Application Services | B7: =Assumptions!C18 -> 3902.21 | C7: =B7*(1+Assumptions!$C$31*Assumptions!$F$18^0)*(1+Assumptions!$B$31*Assumptions!B$38) -> 4163.6581 | D7: =C7*(1+Assumptions!$C$31*Assumptions!$F$18^1)*(1+Assumptions!$B$31*Assumptions!C$38) -> 4442.6232 | E7: =D7*(1+Assumptions!$C$31*Assumptions!$F$18^2)*(1+Assumptions!$B$31*Assumptions!D$38) -> 4754.9396 | F7: =E7*(1+Assumptions!$C$31*Assumptions!$F$18^3)*(1+Assumptions!$B$31*Assumptions!E$38) -> 5089.2118 | G7: =F7*(1+Assumptions!$C$31*Assumptions!$F$18^4)*(1+Assumptions!$B$31*Assumptions!F$38) -> 5463.7778
A8: Cloud & Infrastructure Managed Services | B8: =Assumptions!C19 -> 4802.72 | C8: =B8*(1+Assumptions!$C$32*Assumptions!$F$19^0)*(1+Assumptions!$B$32*Assumptions!B$38) -> 5163.8845 | D8: =C8*(1+Assumptions!$C$32*Assumptions!$F$19^1)*(1+Assumptions!$B$32*Assumptions!C$38) -> 5552.2087 | E8: =D8*(1+Assumptions!$C$32*Assumptions!$F$19^2)*(1+Assumptions!$B$32*Assumptions!D$38) -> 5994.6086 | F8: =E8*(1+Assumptions!$C$32*Assumptions!$F$19^3)*(1+Assumptions!$B$32*Assumptions!E$38) -> 6472.2591 | G8: =F8*(1+Assumptions!$C$32*Assumptions!$F$19^4)*(1+Assumptions!$B$32*Assumptions!F$38) -> 7016.9644
A9: Business Process Services | B9: =Assumptions!C20 -> 3001.7 | C9: =B9*(1+Assumptions!$C$33*Assumptions!$F$20^0)*(1+Assumptions!$B$33*Assumptions!B$38) -> 3103.7578 | D9: =C9*(1+Assumptions!$C$33*Assumptions!$F$20^1)*(1+Assumptions!$B$33*Assumptions!C$38) -> 3209.2856 | E9: =D9*(1+Assumptions!$C$33*Assumptions!$F$20^2)*(1+Assumptions!$B$33*Assumptions!D$38) -> 3339.5826 | F9: =E9*(1+Assumptions!$C$33*Assumptions!$F$20^3)*(1+Assumptions!$B$33*Assumptions!E$38) -> 3475.1696 | G9: =F9*(1+Assumptions!$C$33*Assumptions!$F$20^4)*(1+Assumptions!$B$33*Assumptions!F$38) -> 3639.1976
A10: Engineering & R&D Services | B10: =Assumptions!C21 -> 2701.53 | C10: =B10*(1+Assumptions!$C$34*Assumptions!$F$21^0)*(1+Assumptions!$B$34*Assumptions!B$38) -> 2995.4565 | D10: =C10*(1+Assumptions!$C$34*Assumptions!$F$21^1)*(1+Assumptions!$B$34*Assumptions!C$38) -> 3321.3621 | E10: =D10*(1+Assumptions!$C$34*Assumptions!$F$21^2)*(1+Assumptions!$B$34*Assumptions!D$38) -> 3686.4463 | F10: =E10*(1+Assumptions!$C$34*Assumptions!$F$21^3)*(1+Assumptions!$B$34*Assumptions!E$38) -> 4091.6604 | G10: =F10*(1+Assumptions!$C$34*Assumptions!$F$21^4)*(1+Assumptions!$B$34*Assumptions!F$38) -> 4545.9984
A11: Consulting, Data, AI & Cybersecurity | B11: =Assumptions!C22 -> 4502.55 | C11: =B11*(1+Assumptions!$C$35*Assumptions!$F$22^0)*(1+Assumptions!$B$35*Assumptions!B$38) -> 5673.213 | D11: =C11*(1+Assumptions!$C$35*Assumptions!$F$22^1)*(1+Assumptions!$B$35*Assumptions!C$38) -> 6971.2441 | E11: =D11*(1+Assumptions!$C$35*Assumptions!$F$22^2)*(1+Assumptions!$B$35*Assumptions!D$38) -> 8374.8623 | F11: =E11*(1+Assumptions!$C$35*Assumptions!$F$22^3)*(1+Assumptions!$B$35*Assumptions!E$38) -> 9858.7432 | G11: =F11*(1+Assumptions!$C$35*Assumptions!$F$22^4)*(1+Assumptions!$B$35*Assumptions!F$38) -> 11395.926
A12: Products & Platforms (BaNCS, ignio, iON, ADD) | B12: =Assumptions!C23 -> 1500.85 | C12: =B12*(1+Assumptions!$C$36*Assumptions!$F$23^0)*(1+Assumptions!$B$36*Assumptions!B$38) -> 1740.986 | D12: =C12*(1+Assumptions!$C$36*Assumptions!$F$23^1)*(1+Assumptions!$B$36*Assumptions!C$38) -> 1997.2591 | E12: =D12*(1+Assumptions!$C$36*Assumptions!$F$23^2)*(1+Assumptions!$B$36*Assumptions!D$38) -> 2267.736 | F12: =E12*(1+Assumptions!$C$36*Assumptions!$F$23^3)*(1+Assumptions!$B$36*Assumptions!E$38) -> 2550.2734 | G12: =F12*(1+Assumptions!$C$36*Assumptions!$F$23^4)*(1+Assumptions!$B$36*Assumptions!F$38) -> 2842.593
A13: Total revenue ($mn) | B13: =SUM(B6:B12) -> 30017 | C13: =SUM(C6:C12) -> 32787.389 | D13: =SUM(D6:D12) -> 35793.514 | E13: =SUM(E6:E12) -> 39139.473 | F13: =SUM(F6:F12) -> 42697.652 | G13: =SUM(G6:G12) -> 46582.631
A14: Growth, constant currency | C14: =C13/B13-1 -> 0.092294 | D14: =D13/C13-1 -> 0.091685413 | E14: =E13/D13-1 -> 0.093479458 | F14: =F13/E13-1 -> 0.090910252 | G14: =G13/F13-1 -> 0.090988131
A15: FY26–FY31 revenue CAGR | C15: =(G13/B13)^(1/5)-1 -> 0.091871038
A18: Base — Managed Transition
A19: Exposure bucket | B19: FY26 | C19: FY27 | D19: FY28 | E19: FY29 | F19: FY30 | G19: FY31
A20: Application Development & Maintenance (custom) | B20: =Assumptions!C17 -> 9605.44 | C20: =B20*(1+Assumptions!$C$47*Assumptions!$F$17^0)*(1+Assumptions!$B$47*Assumptions!B$55) -> 9570.8604 | D20: =C20*(1+Assumptions!$C$47*Assumptions!$F$17^1)*(1+Assumptions!$B$47*Assumptions!C$55) -> 9536.4053 | E20: =D20*(1+Assumptions!$C$47*Assumptions!$F$17^2)*(1+Assumptions!$B$47*Assumptions!D$55) -> 9502.0743 | F20: =E20*(1+Assumptions!$C$47*Assumptions!$F$17^3)*(1+Assumptions!$B$47*Assumptions!E$55) -> 9528.3 | G20: =F20*(1+Assumptions!$C$47*Assumptions!$F$17^4)*(1+Assumptions!$B$47*Assumptions!F$55) -> 9554.5981
A21: Enterprise / Package Application Services | B21: =Assumptions!C18 -> 3902.21 | C21: =B21*(1+Assumptions!$C$48*Assumptions!$F$18^0)*(1+Assumptions!$B$48*Assumptions!B$55) -> 4008.3501 | D21: =C21*(1+Assumptions!$C$48*Assumptions!$F$18^1)*(1+Assumptions!$B$48*Assumptions!C$55) -> 4117.3772 | E21: =D21*(1+Assumptions!$C$48*Assumptions!$F$18^2)*(1+Assumptions!$B$48*Assumptions!D$55) -> 4229.3699 | F21: =E21*(1+Assumptions!$C$48*Assumptions!$F$18^3)*(1+Assumptions!$B$48*Assumptions!E$55) -> 4362.5105 | G21: =F21*(1+Assumptions!$C$48*Assumptions!$F$18^4)*(1+Assumptions!$B$48*Assumptions!F$55) -> 4499.8423
A22: Cloud & Infrastructure Managed Services | B22: =Assumptions!C19 -> 4802.72 | C22: =B22*(1+Assumptions!$C$49*Assumptions!$F$19^0)*(1+Assumptions!$B$49*Assumptions!B$55) -> 4927.5907 | D22: =C22*(1+Assumptions!$C$49*Assumptions!$F$19^1)*(1+Assumptions!$B$49*Assumptions!C$55) -> 5055.7081 | E22: =D22*(1+Assumptions!$C$49*Assumptions!$F$19^2)*(1+Assumptions!$B$49*Assumptions!D$55) -> 5187.1565 | F22: =E22*(1+Assumptions!$C$49*Assumptions!$F$19^3)*(1+Assumptions!$B$49*Assumptions!E$55) -> 5350.0332 | G22: =F22*(1+Assumptions!$C$49*Assumptions!$F$19^4)*(1+Assumptions!$B$49*Assumptions!F$55) -> 5518.0242
A23: Business Process Services | B23: =Assumptions!C20 -> 3001.7 | C23: =B23*(1+Assumptions!$C$50*Assumptions!$F$20^0)*(1+Assumptions!$B$50*Assumptions!B$55) -> 2927.2578 | D23: =C23*(1+Assumptions!$C$50*Assumptions!$F$20^1)*(1+Assumptions!$B$50*Assumptions!C$55) -> 2854.6618 | E23: =D23*(1+Assumptions!$C$50*Assumptions!$F$20^2)*(1+Assumptions!$B$50*Assumptions!D$55) -> 2783.8662 | F23: =E23*(1+Assumptions!$C$50*Assumptions!$F$20^3)*(1+Assumptions!$B$50*Assumptions!E$55) -> 2738.4335 | G23: =F23*(1+Assumptions!$C$50*Assumptions!$F$20^4)*(1+Assumptions!$B$50*Assumptions!F$55) -> 2693.7423
A24: Engineering & R&D Services | B24: =Assumptions!C21 -> 2701.53 | C24: =B24*(1+Assumptions!$C$51*Assumptions!$F$21^0)*(1+Assumptions!$B$51*Assumptions!B$55) -> 2859.2994 | D24: =C24*(1+Assumptions!$C$51*Assumptions!$F$21^1)*(1+Assumptions!$B$51*Assumptions!C$55) -> 3026.2824 | E24: =D24*(1+Assumptions!$C$51*Assumptions!$F$21^2)*(1+Assumptions!$B$51*Assumptions!D$55) -> 3203.0173 | F24: =E24*(1+Assumptions!$C$51*Assumptions!$F$21^3)*(1+Assumptions!$B$51*Assumptions!E$55) -> 3396.9921 | G24: =F24*(1+Assumptions!$C$51*Assumptions!$F$21^4)*(1+Assumptions!$B$51*Assumptions!F$55) -> 3602.7139
A25: Consulting, Data, AI & Cybersecurity | B25: =Assumptions!C22 -> 4502.55 | C25: =B25*(1+Assumptions!$C$52*Assumptions!$F$22^0)*(1+Assumptions!$B$52*Assumptions!B$55) -> 5206.7488 | D25: =C25*(1+Assumptions!$C$52*Assumptions!$F$22^1)*(1+Assumptions!$B$52*Assumptions!C$55) -> 5910.8679 | E25: =D25*(1+Assumptions!$C$52*Assumptions!$F$22^2)*(1+Assumptions!$B$52*Assumptions!D$55) -> 6600.0997 | F25: =E25*(1+Assumptions!$C$52*Assumptions!$F$22^3)*(1+Assumptions!$B$52*Assumptions!E$55) -> 7276.326 | G25: =F25*(1+Assumptions!$C$52*Assumptions!$F$22^4)*(1+Assumptions!$B$52*Assumptions!F$55) -> 7916.6584
A26: Products & Platforms (BaNCS, ignio, iON, ADD) | B26: =Assumptions!C23 -> 1500.85 | C26: =B26*(1+Assumptions!$C$53*Assumptions!$F$23^0)*(1+Assumptions!$B$53*Assumptions!B$55) -> 1649.2841 | D26: =C26*(1+Assumptions!$C$53*Assumptions!$F$23^1)*(1+Assumptions!$B$53*Assumptions!C$55) -> 1798.0297 | E26: =D26*(1+Assumptions!$C$53*Assumptions!$F$23^2)*(1+Assumptions!$B$53*Assumptions!D$55) -> 1945.7791 | F26: =E26*(1+Assumptions!$C$53*Assumptions!$F$23^3)*(1+Assumptions!$B$53*Assumptions!E$55) -> 2093.4341 | G26: =F26*(1+Assumptions!$C$53*Assumptions!$F$23^4)*(1+Assumptions!$B$53*Assumptions!F$55) -> 2238.0779
A27: Total revenue ($mn) | B27: =SUM(B20:B26) -> 30017 | C27: =SUM(C20:C26) -> 31149.391 | D27: =SUM(D20:D26) -> 32299.332 | E27: =SUM(E20:E26) -> 33451.363 | F27: =SUM(F20:F26) -> 34746.029 | G27: =SUM(G20:G26) -> 36023.657
A28: Growth, constant currency | C28: =C27/B27-1 -> 0.037725 | D28: =D27/C27-1 -> 0.03691697 | E28: =E27/D27-1 -> 0.035667316 | F28: =F27/E27-1 -> 0.038702949 | G28: =G27/F27-1 -> 0.036770465
A29: FY26–FY31 revenue CAGR | C29: =(G27/B27)^(1/5)-1 -> 0.037156045
A32: Bear — Slow Bleed
A33: Exposure bucket | B33: FY26 | C33: FY27 | D33: FY28 | E33: FY29 | F33: FY30 | G33: FY31
A34: Application Development & Maintenance (custom) | B34: =Assumptions!C17 -> 9605.44 | C34: =B34*(1+Assumptions!$C$64*Assumptions!$F$17^0)*(1+Assumptions!$B$64*Assumptions!B$72) -> 9092.1253 | D34: =C34*(1+Assumptions!$C$64*Assumptions!$F$17^1)*(1+Assumptions!$B$64*Assumptions!C$72) -> 8439.3107 | E34: =D34*(1+Assumptions!$C$64*Assumptions!$F$17^2)*(1+Assumptions!$B$64*Assumptions!D$72) -> 7755.8953 | F34: =E34*(1+Assumptions!$C$64*Assumptions!$F$17^3)*(1+Assumptions!$B$64*Assumptions!E$72) -> 7199.022 | G34: =F34*(1+Assumptions!$C$64*Assumptions!$F$17^4)*(1+Assumptions!$B$64*Assumptions!F$72) -> 6748.2193
A35: Enterprise / Package Application Services | B35: =Assumptions!C18 -> 3902.21 | C35: =B35*(1+Assumptions!$C$65*Assumptions!$F$18^0)*(1+Assumptions!$B$65*Assumptions!B$72) -> 3826.351 | D35: =C35*(1+Assumptions!$C$65*Assumptions!$F$18^1)*(1+Assumptions!$B$65*Assumptions!C$72) -> 3704.6731 | E35: =D35*(1+Assumptions!$C$65*Assumptions!$F$18^2)*(1+Assumptions!$B$65*Assumptions!D$72) -> 3563.9696 | F35: =E35*(1+Assumptions!$C$65*Assumptions!$F$18^3)*(1+Assumptions!$B$65*Assumptions!E$72) -> 3450.6354 | G35: =F35*(1+Assumptions!$C$65*Assumptions!$F$18^4)*(1+Assumptions!$B$65*Assumptions!F$72) -> 3362.2301
A36: Cloud & Infrastructure Managed Services | B36: =Assumptions!C19 -> 4802.72 | C36: =B36*(1+Assumptions!$C$66*Assumptions!$F$19^0)*(1+Assumptions!$B$66*Assumptions!B$72) -> 4675.1598 | D36: =C36*(1+Assumptions!$C$66*Assumptions!$F$19^1)*(1+Assumptions!$B$66*Assumptions!C$72) -> 4473.1929 | E36: =D36*(1+Assumptions!$C$66*Assumptions!$F$19^2)*(1+Assumptions!$B$66*Assumptions!D$72) -> 4242.734 | F36: =E36*(1+Assumptions!$C$66*Assumptions!$F$19^3)*(1+Assumptions!$B$66*Assumptions!E$72) -> 4059.4479 | G36: =F36*(1+Assumptions!$C$66*Assumptions!$F$19^4)*(1+Assumptions!$B$66*Assumptions!F$72) -> 3917.8543
A37: Business Process Services | B37: =Assumptions!C20 -> 3001.7 | C37: =B37*(1+Assumptions!$C$67*Assumptions!$F$20^0)*(1+Assumptions!$B$67*Assumptions!B$72) -> 2767.8075 | D37: =C37*(1+Assumptions!$C$67*Assumptions!$F$20^1)*(1+Assumptions!$B$67*Assumptions!C$72) -> 2484.384 | E37: =D37*(1+Assumptions!$C$67*Assumptions!$F$20^2)*(1+Assumptions!$B$67*Assumptions!D$72) -> 2199.5743 | F37: =E37*(1+Assumptions!$C$67*Assumptions!$F$20^3)*(1+Assumptions!$B$67*Assumptions!E$72) -> 1974.3379 | G37: =F37*(1+Assumptions!$C$67*Assumptions!$F$20^4)*(1+Assumptions!$B$67*Assumptions!F$72) -> 1796.3316
A38: Engineering & R&D Services | B38: =Assumptions!C21 -> 2701.53 | C38: =B38*(1+Assumptions!$C$68*Assumptions!$F$21^0)*(1+Assumptions!$B$68*Assumptions!B$72) -> 2719.6843 | D38: =C38*(1+Assumptions!$C$68*Assumptions!$F$21^1)*(1+Assumptions!$B$68*Assumptions!C$72) -> 2715.3328 | E38: =D38*(1+Assumptions!$C$68*Assumptions!$F$21^2)*(1+Assumptions!$B$68*Assumptions!D$72) -> 2699.6925 | F38: =E38*(1+Assumptions!$C$68*Assumptions!$F$21^3)*(1+Assumptions!$B$68*Assumptions!E$72) -> 2695.373 | G38: =F38*(1+Assumptions!$C$68*Assumptions!$F$21^4)*(1+Assumptions!$B$68*Assumptions!F$72) -> 2702.2731
A39: Consulting, Data, AI & Cybersecurity | B39: =Assumptions!C22 -> 4502.55 | C39: =B39*(1+Assumptions!$C$69*Assumptions!$F$22^0)*(1+Assumptions!$B$69*Assumptions!B$72) -> 4837.8999 | D39: =C39*(1+Assumptions!$C$69*Assumptions!$F$22^1)*(1+Assumptions!$B$69*Assumptions!C$72) -> 5093.9603 | E39: =D39*(1+Assumptions!$C$69*Assumptions!$F$22^2)*(1+Assumptions!$B$69*Assumptions!D$72) -> 5284.6573 | F39: =E39*(1+Assumptions!$C$69*Assumptions!$F$22^3)*(1+Assumptions!$B$69*Assumptions!E$72) -> 5453.5731 | G39: =F39*(1+Assumptions!$C$69*Assumptions!$F$22^4)*(1+Assumptions!$B$69*Assumptions!F$72) -> 5604.0465
A40: Products & Platforms (BaNCS, ignio, iON, ADD) | B40: =Assumptions!C23 -> 1500.85 | C40: =B40*(1+Assumptions!$C$70*Assumptions!$F$23^0)*(1+Assumptions!$B$70*Assumptions!B$72) -> 1552.7194 | D40: =C40*(1+Assumptions!$C$70*Assumptions!$F$23^1)*(1+Assumptions!$B$70*Assumptions!C$72) -> 1589.2766 | E40: =D40*(1+Assumptions!$C$70*Assumptions!$F$23^2)*(1+Assumptions!$B$70*Assumptions!D$72) -> 1614.8769 | F40: =E40*(1+Assumptions!$C$70*Assumptions!$F$23^3)*(1+Assumptions!$B$70*Assumptions!E$72) -> 1639.6162 | G40: =F40*(1+Assumptions!$C$70*Assumptions!$F$23^4)*(1+Assumptions!$B$70*Assumptions!F$72) -> 1663.9203
A41: Total revenue ($mn) | B41: =SUM(B34:B40) -> 30017 | C41: =SUM(C34:C40) -> 29471.747 | D41: =SUM(D34:D40) -> 28500.13 | E41: =SUM(E34:E40) -> 27361.4 | F41: =SUM(F34:F40) -> 26472.005 | G41: =SUM(G34:G40) -> 25794.875
A42: Growth, constant currency | C42: =C41/B41-1 -> -0.0181648 | D42: =D41/C41-1 -> -0.032967738 | E42: =E41/D41-1 -> -0.039955276 | F42: =F41/E41-1 -> -0.032505441 | G42: =G41/F41-1 -> -0.02557911
A43: FY26–FY31 revenue CAGR | C43: =(G41/B41)^(1/5)-1 -> -0.029862642
A46: Severe — Structural Break
A47: Exposure bucket | B47: FY26 | C47: FY27 | D47: FY28 | E47: FY29 | F47: FY30 | G47: FY31
A48: Application Development & Maintenance (custom) | B48: =Assumptions!C17 -> 9605.44 | C48: =B48*(1+Assumptions!$C$81*Assumptions!$F$17^0)*(1+Assumptions!$B$81*Assumptions!B$89) -> 8856.2157 | D48: =C48*(1+Assumptions!$C$81*Assumptions!$F$17^1)*(1+Assumptions!$B$81*Assumptions!C$89) -> 7704.9076 | E48: =D48*(1+Assumptions!$C$81*Assumptions!$F$17^2)*(1+Assumptions!$B$81*Assumptions!D$89) -> 6502.942 | F48: =E48*(1+Assumptions!$C$81*Assumptions!$F$17^3)*(1+Assumptions!$B$81*Assumptions!E$89) -> 5573.0213 | G48: =F48*(1+Assumptions!$C$81*Assumptions!$F$17^4)*(1+Assumptions!$B$81*Assumptions!F$89) -> 4920.9778
A49: Enterprise / Package Application Services | B49: =Assumptions!C18 -> 3902.21 | C49: =B49*(1+Assumptions!$C$82*Assumptions!$F$18^0)*(1+Assumptions!$B$82*Assumptions!B$89) -> 3691.4907 | D49: =C49*(1+Assumptions!$C$82*Assumptions!$F$18^1)*(1+Assumptions!$B$82*Assumptions!C$89) -> 3359.2565 | E49: =D49*(1+Assumptions!$C$82*Assumptions!$F$18^2)*(1+Assumptions!$B$82*Assumptions!D$89) -> 2996.4568 | F49: =E49*(1+Assumptions!$C$82*Assumptions!$F$18^3)*(1+Assumptions!$B$82*Assumptions!E$89) -> 2699.8076 | G49: =F49*(1+Assumptions!$C$82*Assumptions!$F$18^4)*(1+Assumptions!$B$82*Assumptions!F$89) -> 2481.1232
A50: Cloud & Infrastructure Managed Services | B50: =Assumptions!C19 -> 4802.72 | C50: =B50*(1+Assumptions!$C$83*Assumptions!$F$19^0)*(1+Assumptions!$B$83*Assumptions!B$89) -> 4530.5979 | D50: =C50*(1+Assumptions!$C$83*Assumptions!$F$19^1)*(1+Assumptions!$B$83*Assumptions!C$89) -> 4072.5544 | E50: =D50*(1+Assumptions!$C$83*Assumptions!$F$19^2)*(1+Assumptions!$B$83*Assumptions!D$89) -> 3570.327 | F50: =E50*(1+Assumptions!$C$83*Assumptions!$F$19^3)*(1+Assumptions!$B$83*Assumptions!E$89) -> 3169.7006 | G50: =F50*(1+Assumptions!$C$83*Assumptions!$F$19^4)*(1+Assumptions!$B$83*Assumptions!F$89) -> 2884.4593
A51: Business Process Services | B51: =Assumptions!C20 -> 3001.7 | C51: =B51*(1+Assumptions!$C$84*Assumptions!$F$20^0)*(1+Assumptions!$B$84*Assumptions!B$89) -> 2623.9661 | D51: =C51*(1+Assumptions!$C$84*Assumptions!$F$20^1)*(1+Assumptions!$B$84*Assumptions!C$89) -> 2108.6191 | E51: =D51*(1+Assumptions!$C$84*Assumptions!$F$20^2)*(1+Assumptions!$B$84*Assumptions!D$89) -> 1620.0943 | F51: =E51*(1+Assumptions!$C$84*Assumptions!$F$20^3)*(1+Assumptions!$B$84*Assumptions!E$89) -> 1273.3293 | G51: =F51*(1+Assumptions!$C$84*Assumptions!$F$20^4)*(1+Assumptions!$B$84*Assumptions!F$89) -> 1045.7089
A52: Engineering & R&D Services | B52: =Assumptions!C21 -> 2701.53 | C52: =B52*(1+Assumptions!$C$85*Assumptions!$F$21^0)*(1+Assumptions!$B$85*Assumptions!B$89) -> 2630.3177 | D52: =C52*(1+Assumptions!$C$85*Assumptions!$F$21^1)*(1+Assumptions!$B$85*Assumptions!C$89) -> 2497.2236 | E52: =D52*(1+Assumptions!$C$85*Assumptions!$F$21^2)*(1+Assumptions!$B$85*Assumptions!D$89) -> 2340.5977 | F52: =E52*(1+Assumptions!$C$85*Assumptions!$F$21^3)*(1+Assumptions!$B$85*Assumptions!E$89) -> 2207.9795 | G52: =F52*(1+Assumptions!$C$85*Assumptions!$F$21^4)*(1+Assumptions!$B$85*Assumptions!F$89) -> 2109.6361
A53: Consulting, Data, AI & Cybersecurity | B53: =Assumptions!C22 -> 4502.55 | C53: =B53*(1+Assumptions!$C$86*Assumptions!$F$22^0)*(1+Assumptions!$B$86*Assumptions!B$89) -> 4529.115 | D53: =C53*(1+Assumptions!$C$86*Assumptions!$F$22^1)*(1+Assumptions!$B$86*Assumptions!C$89) -> 4397.4084 | E53: =D53*(1+Assumptions!$C$86*Assumptions!$F$22^2)*(1+Assumptions!$B$86*Assumptions!D$89) -> 4183.9912 | F53: =E53*(1+Assumptions!$C$86*Assumptions!$F$22^3)*(1+Assumptions!$B$86*Assumptions!E$89) -> 3993.4102 | G53: =F53*(1+Assumptions!$C$86*Assumptions!$F$22^4)*(1+Assumptions!$B$86*Assumptions!F$89) -> 3854.0231
A54: Products & Platforms (BaNCS, ignio, iON, ADD) | B54: =Assumptions!C23 -> 1500.85 | C54: =B54*(1+Assumptions!$C$87*Assumptions!$F$23^0)*(1+Assumptions!$B$87*Assumptions!B$89) -> 1475.7558 | D54: =C54*(1+Assumptions!$C$87*Assumptions!$F$23^1)*(1+Assumptions!$B$87*Assumptions!C$89) -> 1412.7351 | E54: =D54*(1+Assumptions!$C$87*Assumptions!$F$23^2)*(1+Assumptions!$B$87*Assumptions!D$89) -> 1333.2111 | F54: =E54*(1+Assumptions!$C$87*Assumptions!$F$23^3)*(1+Assumptions!$B$87*Assumptions!E$89) -> 1264.6119 | G54: =F54*(1+Assumptions!$C$87*Assumptions!$F$23^4)*(1+Assumptions!$B$87*Assumptions!F$89) -> 1213.4636
A55: Total revenue ($mn) | B55: =SUM(B48:B54) -> 30017 | C55: =SUM(C48:C54) -> 28337.459 | D55: =SUM(D48:D54) -> 25552.705 | E55: =SUM(E48:E54) -> 22547.62 | F55: =SUM(F48:F54) -> 20181.86 | G55: =SUM(G48:G54) -> 18509.392
A56: Growth, constant currency | C56: =C55/B55-1 -> -0.055953 | D56: =D55/C55-1 -> -0.098271126 | E56: =E55/D55-1 -> -0.11760339 | F56: =F55/E55-1 -> -0.10492282 | G56: =G55/F55-1 -> -0.082869882
A57: FY26–FY31 revenue CAGR | C57: =(G55/B55)^(1/5)-1 -> -0.092169074

Sheet Scenario Output
A1: Scenario output — P&L, cash, dividend and headcount
A2: FY26 column is actual. FY27–FY31 are model output.
A4: Bull — AI Dividend
B5: FY26A | C5: FY27 | D5: FY28 | E5: FY29 | F5: FY30 | G5: FY31
A6: Revenue ($mn) | B6: 30017 | C6: ='Revenue Build'!C13 -> 32787.389 | D6: ='Revenue Build'!D13 -> 35793.514 | E6: ='Revenue Build'!E13 -> 39139.473 | F6: ='Revenue Build'!F13 -> 42697.652 | G6: ='Revenue Build'!G13 -> 46582.631
A7: growth, constant currency | C7: =C6/B6-1 -> 0.092294 | D7: =D6/C6-1 -> 0.091685413 | E7: =E6/D6-1 -> 0.093479458 | F7: =F6/E6-1 -> 0.090910252 | G7: =G6/F6-1 -> 0.090988131
A8: Operating margin | B8: 0.25 | C8: =Assumptions!B39 -> 0.245 | D8: =Assumptions!C39 -> 0.255 | E8: =Assumptions!D39 -> 0.262 | F8: =Assumptions!E39 -> 0.267 | G8: =Assumptions!F39 -> 0.27
A9: Operating income ($mn) | B9: =B6*B8 -> 7504.25 | C9: =C6*C8 -> 8032.9103 | D9: =D6*D8 -> 9127.3461 | E9: =E6*E8 -> 10254.542 | F9: =F6*F8 -> 11400.273 | G9: =G6*G8 -> 12577.31
A10: Profit before tax ($mn) | C10: =C6*(C8+Assumptions!$B$10) -> 8557.5085 | D10: =D6*(D8+Assumptions!$B$10) -> 9700.0424 | E10: =E6*(E8+Assumptions!$B$10) -> 10880.773 | F10: =F6*(F8+Assumptions!$B$10) -> 12083.435 | G10: =G6*(G8+Assumptions!$B$10) -> 13322.633
A11: Net income ($mn) | B11: 5938 | C11: =C10*(1-Assumptions!$B$11) -> 6375.3439 | D11: =D10*(1-Assumptions!$B$11) -> 7226.5316 | E11: =E10*(1-Assumptions!$B$11) -> 8106.1762 | F11: =F10*(1-Assumptions!$B$11) -> 9002.1594 | G11: =G10*(1-Assumptions!$B$11) -> 9925.3613
A12: net margin | B12: 0.198 | C12: =C11/C6 -> 0.194445 | D12: =D11/D6 -> 0.201895 | E12: =E11/E6 -> 0.20711 | F12: =F11/F6 -> 0.210835 | G12: =G11/G6 -> 0.21307
A13: ₹ / US$ | B13: 88.956591 | C13: =B13*(1+Assumptions!$B$9) -> 90.735723 | D13: =C13*(1+Assumptions!$B$9) -> 92.550438 | E13: =D13*(1+Assumptions!$B$9) -> 94.401446 | F13: =E13*(1+Assumptions!$B$9) -> 96.289475 | G13: =F13*(1+Assumptions!$B$9) -> 98.215265
A14: Revenue (₹ crore) | B14: 267021 | C14: =C6*C13/10 -> 297498.74 | D14: =D6*D13/10 -> 331270.54 | E14: =E6*E13/10 -> 369482.28 | F14: =F6*F13/10 -> 411133.45 | G14: =G6*G13/10 -> 457512.55
A15: Net income (₹ crore) | B15: 49454 | C15: =C11*C13/10 -> 57847.143 | D15: =D11*D13/10 -> 66881.866 | E15: =E11*E13/10 -> 76523.475 | F15: =F11*F13/10 -> 86681.321 | G15: =G11*G13/10 -> 97482.199
A16: Free cash flow (₹ crore) | B16: 42983 | C16: =C15*Assumptions!B40 -> 46277.715 | D16: =D15*Assumptions!C40 -> 50161.399 | E16: =E15*Assumptions!D40 -> 60453.546 | F16: =F15*Assumptions!E40 -> 72812.31 | G16: =G15*Assumptions!F40 -> 85784.335
A17: Total dividend (₹ crore) | B17: 39571 | C17: =C16*Assumptions!B41 -> 42575.498 | D17: =D16*Assumptions!C41 -> 46148.487 | E17: =E16*Assumptions!D41 -> 55617.262 | F17: =F16*Assumptions!E41 -> 66987.325 | G17: =G16*Assumptions!F41 -> 78921.588
A18: Dividend per share (₹) | B18: 110 | C18: =C17/Assumptions!$B$13 -> 117.67689 | D18: =D17/Assumptions!$B$13 -> 127.55248 | E18: =E17/Assumptions!$B$13 -> 153.72378 | F18: =F17/Assumptions!$B$13 -> 185.15015 | G18: =G17/Assumptions!$B$13 -> 218.13595
A19: Dividend to Tata Sons (₹ crore) | B19: 28291 | C19: =C17*Assumptions!$B$12 -> 30543.662 | D19: =D17*Assumptions!$B$12 -> 33106.925 | E19: =E17*Assumptions!$B$12 -> 39899.824 | F19: =F17*Assumptions!$B$12 -> 48056.707 | G19: =G17*Assumptions!$B$12 -> 56618.347
A20: Revenue per employee ($) | B20: 51353 | C20: =B20*(1+Assumptions!$B$42) -> 54177.415 | D20: =C20*(1+Assumptions!$B$42) -> 57157.173 | E20: =D20*(1+Assumptions!$B$42) -> 60300.817 | F20: =E20*(1+Assumptions!$B$42) -> 63617.362 | G20: =F20*(1+Assumptions!$B$42) -> 67116.317
A21: Closing headcount | B21: 584519 | C21: =C6*1000000/C20 -> 605185.56 | D21: =D6*1000000/D20 -> 626229.61 | E21: =E6*1000000/E20 -> 649070.35 | F21: =F6*1000000/F20 -> 671163.51 | G21: =G6*1000000/G20 -> 694058.22
A22: change vs FY26 | C22: =C21-$B$21 -> 20666.556 | D22: =D21-$B$21 -> 41710.614 | E22: =E21-$B$21 -> 64551.35 | F22: =F21-$B$21 -> 86644.506 | G22: =G21-$B$21 -> 109539.22
A24: FY26–FY31 revenue CAGR | C24: =(G6/B6)^(1/5)-1 -> 0.091871038
A25: Cumulative dividend to Tata Sons, FY27–FY31 (₹ crore) | C25: =SUM(C19:G19) -> 208225.46
A28: Base — Managed Transition
B29: FY26A | C29: FY27 | D29: FY28 | E29: FY29 | F29: FY30 | G29: FY31
A30: Revenue ($mn) | B30: 30017 | C30: ='Revenue Build'!C27 -> 31149.391 | D30: ='Revenue Build'!D27 -> 32299.332 | E30: ='Revenue Build'!E27 -> 33451.363 | F30: ='Revenue Build'!F27 -> 34746.029 | G30: ='Revenue Build'!G27 -> 36023.657
A31: growth, constant currency | C31: =C30/B30-1 -> 0.037725 | D31: =D30/C30-1 -> 0.03691697 | E31: =E30/D30-1 -> 0.035667316 | F31: =F30/E30-1 -> 0.038702949 | G31: =G30/F30-1 -> 0.036770465
A32: Operating margin | B32: 0.25 | C32: =Assumptions!B56 -> 0.243 | D32: =Assumptions!C56 -> 0.246 | E32: =Assumptions!D56 -> 0.25 | F32: =Assumptions!E56 -> 0.252 | G32: =Assumptions!F56 -> 0.255
A33: Operating income ($mn) | B33: =B30*B32 -> 7504.25 | C33: =C30*C32 -> 7569.3021 | D33: =D30*D32 -> 7945.6358 | E33: =E30*E32 -> 8362.8407 | F33: =F30*F32 -> 8755.9994 | G33: =G30*G32 -> 9186.0325
A34: Profit before tax ($mn) | C34: =C30*(C32+Assumptions!$B$10) -> 8067.6924 | D34: =D30*(D32+Assumptions!$B$10) -> 8462.4251 | E34: =E30*(E32+Assumptions!$B$10) -> 8898.0626 | F34: =F30*(F32+Assumptions!$B$10) -> 9311.9359 | G34: =G30*(G32+Assumptions!$B$10) -> 9762.4111
A35: Net income ($mn) | B35: 5938 | C35: =C34*(1-Assumptions!$B$11) -> 6010.4308 | D35: =D34*(1-Assumptions!$B$11) -> 6304.5067 | E35: =E34*(1-Assumptions!$B$11) -> 6629.0566 | F35: =F34*(1-Assumptions!$B$11) -> 6937.3922 | G35: =G34*(1-Assumptions!$B$11) -> 7272.9962
A36: net margin | B36: 0.198 | C36: =C35/C30 -> 0.192955 | D36: =D35/D30 -> 0.19519 | E36: =E35/E30 -> 0.19817 | F36: =F35/F30 -> 0.19966 | G36: =G35/G30 -> 0.201895
A37: ₹ / US$ | B37: 88.956591 | C37: =B37*(1+Assumptions!$B$9) -> 90.735723 | D37: =C37*(1+Assumptions!$B$9) -> 92.550438 | E37: =D37*(1+Assumptions!$B$9) -> 94.401446 | F37: =E37*(1+Assumptions!$B$9) -> 96.289475 | G37: =F37*(1+Assumptions!$B$9) -> 98.215265
A38: Revenue (₹ crore) | B38: 267021 | C38: =C30*C37/10 -> 282636.25 | D38: =D30*D37/10 -> 298931.74 | E38: =E30*E37/10 -> 315785.7 | F38: =F30*F37/10 -> 334567.69 | G38: =G30*G37/10 -> 353807.3
A39: Net income (₹ crore) | B39: 49454 | C39: =C35*C37/10 -> 54536.079 | D39: =D35*D37/10 -> 58348.485 | E39: =E35*E37/10 -> 62579.253 | F39: =F35*F37/10 -> 66799.786 | G39: =G35*G37/10 -> 71431.925
A40: Free cash flow (₹ crore) | B40: 42983 | C40: =C39*Assumptions!B57 -> 43628.863 | D40: =D39*Assumptions!C57 -> 44344.849 | E40: =E39*Assumptions!D57 -> 48811.817 | F40: =F39*Assumptions!E57 -> 54775.824 | G40: =G39*Assumptions!F57 -> 60717.136
A41: Total dividend (₹ crore) | B41: 39571 | C41: =C40*Assumptions!B58 -> 40574.842 | D41: =D40*Assumptions!C58 -> 41240.71 | E41: =E40*Assumptions!D58 -> 44906.872 | F41: =F40*Assumptions!E58 -> 50393.758 | G41: =G40*Assumptions!F58 -> 55859.765
A42: Dividend per share (₹) | B42: 110 | C42: =C41/Assumptions!$B$13 -> 112.14716 | D42: =D41/Assumptions!$B$13 -> 113.98759 | E42: =E41/Assumptions!$B$13 -> 124.12071 | F42: =F41/Assumptions!$B$13 -> 139.28623 | G42: =G41/Assumptions!$B$13 -> 154.39404
A43: Dividend to Tata Sons (₹ crore) | B43: 28291 | C43: =C41*Assumptions!$B$12 -> 29108.392 | D43: =D41*Assumptions!$B$12 -> 29586.085 | E43: =E41*Assumptions!$B$12 -> 32216.19 | F43: =F41*Assumptions!$B$12 -> 36152.482 | G43: =G41*Assumptions!$B$12 -> 40073.796
A44: Revenue per employee ($) | B44: 51353 | C44: =B44*(1+Assumptions!$B$59) -> 53407.12 | D44: =C44*(1+Assumptions!$B$59) -> 55543.405 | E44: =D44*(1+Assumptions!$B$59) -> 57765.141 | F44: =E44*(1+Assumptions!$B$59) -> 60075.747 | G44: =F44*(1+Assumptions!$B$59) -> 62478.776
A45: Closing headcount | B45: 584519 | C45: =C30*1000000/C44 -> 583244.17 | D45: =D30*1000000/D44 -> 581515.17 | E45: =E30*1000000/E44 -> 579092.55 | F45: =F30*1000000/F44 -> 578370.33 | G45: =G30*1000000/G44 -> 576574.3
A46: change vs FY26 | C46: =C45-$B$45 -> -1274.831 | D46: =D45-$B$45 -> -3003.83 | E46: =E45-$B$45 -> -5426.4468 | F46: =F45-$B$45 -> -6148.6703 | G46: =G45-$B$45 -> -7944.6964
A48: FY26–FY31 revenue CAGR | C48: =(G30/B30)^(1/5)-1 -> 0.037156045
A49: Cumulative dividend to Tata Sons, FY27–FY31 (₹ crore) | C49: =SUM(C43:G43) -> 167136.94
A52: Bear — Slow Bleed
B53: FY26A | C53: FY27 | D53: FY28 | E53: FY29 | F53: FY30 | G53: FY31
A54: Revenue ($mn) | B54: 30017 | C54: ='Revenue Build'!C41 -> 29471.747 | D54: ='Revenue Build'!D41 -> 28500.13 | E54: ='Revenue Build'!E41 -> 27361.4 | F54: ='Revenue Build'!F41 -> 26472.005 | G54: ='Revenue Build'!G41 -> 25794.875
A55: growth, constant currency | C55: =C54/B54-1 -> -0.0181648 | D55: =D54/C54-1 -> -0.032967738 | E55: =E54/D54-1 -> -0.039955276 | F55: =F54/E54-1 -> -0.032505441 | G55: =G54/F54-1 -> -0.02557911
A56: Operating margin | B56: 0.25 | C56: =Assumptions!B73 -> 0.24 | D56: =Assumptions!C73 -> 0.234 | E56: =Assumptions!D73 -> 0.228 | F56: =Assumptions!E73 -> 0.224 | G56: =Assumptions!F73 -> 0.22
A57: Operating income ($mn) | B57: =B54*B56 -> 7504.25 | C57: =C54*C56 -> 7073.2193 | D57: =D54*D56 -> 6669.0305 | E57: =E54*E56 -> 6238.3991 | F57: =F54*F56 -> 5929.7292 | G57: =G54*G56 -> 5674.8725
A58: Profit before tax ($mn) | C58: =C54*(C56+Assumptions!$B$10) -> 7544.7673 | D58: =D54*(D56+Assumptions!$B$10) -> 7125.0326 | E58: =E54*(E56+Assumptions!$B$10) -> 6676.1815 | F58: =F54*(F56+Assumptions!$B$10) -> 6353.2813 | G58: =G54*(G56+Assumptions!$B$10) -> 6087.5905
A59: Net income ($mn) | B59: 5938 | C59: =C58*(1-Assumptions!$B$11) -> 5620.8516 | D59: =D58*(1-Assumptions!$B$11) -> 5308.1493 | E59: =E58*(1-Assumptions!$B$11) -> 4973.7552 | F59: =F58*(1-Assumptions!$B$11) -> 4733.1946 | G59: =G58*(1-Assumptions!$B$11) -> 4535.2549
A60: net margin | B60: 0.198 | C60: =C59/C54 -> 0.19072 | D60: =D59/D54 -> 0.18625 | E60: =E59/E54 -> 0.18178 | F60: =F59/F54 -> 0.1788 | G60: =G59/G54 -> 0.17582
A61: ₹ / US$ | B61: 88.956591 | C61: =B61*(1+Assumptions!$B$9) -> 90.735723 | D61: =C61*(1+Assumptions!$B$9) -> 92.550438 | E61: =D61*(1+Assumptions!$B$9) -> 94.401446 | F61: =E61*(1+Assumptions!$B$9) -> 96.289475 | G61: =F61*(1+Assumptions!$B$9) -> 98.215265
A62: Revenue (₹ crore) | B62: 267021 | C62: =C54*C61/10 -> 267414.03 | D62: =D54*D61/10 -> 263769.95 | E62: =E54*E61/10 -> 258295.57 | F62: =F54*F61/10 -> 254897.55 | G62: =G54*G61/10 -> 253345.05
A63: Net income (₹ crore) | B63: 49454 | C63: =C59*C61/10 -> 51001.204 | D63: =D59*D61/10 -> 49127.154 | E63: =E59*E61/10 -> 46952.969 | F63: =F59*F61/10 -> 45575.682 | G63: =G59*G61/10 -> 44543.126
A64: Free cash flow (₹ crore) | B64: 42983 | C64: =C63*Assumptions!B74 -> 39780.939 | D64: =D63*Assumptions!C74 -> 35371.551 | E64: =E63*Assumptions!D74 -> 34745.197 | F64: =F63*Assumptions!E74 -> 35549.032 | G64: =G63*Assumptions!F74 -> 36525.364
A65: Total dividend (₹ crore) | B65: 39571 | C65: =C64*Assumptions!B75 -> 37791.892 | D65: =D64*Assumptions!C75 -> 32895.542 | E65: =E64*Assumptions!D75 -> 31618.129 | F65: =F64*Assumptions!E75 -> 31994.129 | G65: =G64*Assumptions!F75 -> 32872.827
A66: Dividend per share (₹) | B66: 110 | C66: =C65/Assumptions!$B$13 -> 104.4552 | D66: =D65/Assumptions!$B$13 -> 90.921897 | E66: =E65/Assumptions!$B$13 -> 87.391181 | F66: =F65/Assumptions!$B$13 -> 88.430428 | G66: =G65/Assumptions!$B$13 -> 90.859114
A67: Dividend to Tata Sons (₹ crore) | B67: 28291 | C67: =C65*Assumptions!$B$12 -> 27111.903 | D67: =D65*Assumptions!$B$12 -> 23599.262 | E67: =E65*Assumptions!$B$12 -> 22682.846 | F67: =F65*Assumptions!$B$12 -> 22952.588 | G67: =G65*Assumptions!$B$12 -> 23582.966
A68: Revenue per employee ($) | B68: 51353 | C68: =B68*(1+Assumptions!$B$76) -> 52893.59 | D68: =C68*(1+Assumptions!$B$76) -> 54480.398 | E68: =D68*(1+Assumptions!$B$76) -> 56114.81 | F68: =E68*(1+Assumptions!$B$76) -> 57798.254 | G68: =F68*(1+Assumptions!$B$76) -> 59532.202
A69: Closing headcount | B69: 584519 | C69: =C54*1000000/C68 -> 557189.39 | D69: =D54*1000000/D68 -> 523126.33 | E69: =E54*1000000/E68 -> 487596.77 | F69: =F54*1000000/F68 -> 458007.01 | G69: =G54*1000000/G68 -> 433292.81
A70: change vs FY26 | C70: =C69-$B$69 -> -27329.609 | D70: =D69-$B$69 -> -61392.673 | E70: =E69-$B$69 -> -96922.233 | F70: =F69-$B$69 -> -126511.99 | G70: =G69-$B$69 -> -151226.19
A72: FY26–FY31 revenue CAGR | C72: =(G54/B54)^(1/5)-1 -> -0.029862642
A73: Cumulative dividend to Tata Sons, FY27–FY31 (₹ crore) | C73: =SUM(C67:G67) -> 119929.57
A76: Severe — Structural Break
B77: FY26A | C77: FY27 | D77: FY28 | E77: FY29 | F77: FY30 | G77: FY31
A78: Revenue ($mn) | B78: 30017 | C78: ='Revenue Build'!C55 -> 28337.459 | D78: ='Revenue Build'!D55 -> 25552.705 | E78: ='Revenue Build'!E55 -> 22547.62 | F78: ='Revenue Build'!F55 -> 20181.86 | G78: ='Revenue Build'!G55 -> 18509.392
A79: growth, constant currency | C79: =C78/B78-1 -> -0.055953 | D79: =D78/C78-1 -> -0.098271126 | E79: =E78/D78-1 -> -0.11760339 | F79: =F78/E78-1 -> -0.10492282 | G79: =G78/F78-1 -> -0.082869882
A80: Operating margin | B80: 0.25 | C80: =Assumptions!B90 -> 0.235 | D80: =Assumptions!C90 -> 0.22 | E80: =Assumptions!D90 -> 0.202 | F80: =Assumptions!E90 -> 0.188 | G80: =Assumptions!F90 -> 0.175
A81: Operating income ($mn) | B81: =B78*B80 -> 7504.25 | C81: =C78*C80 -> 6659.3028 | D81: =D78*D80 -> 5621.5951 | E81: =E78*E80 -> 4554.6193 | F81: =F78*F80 -> 3794.1897 | G81: =G78*G80 -> 3239.1436
A82: Profit before tax ($mn) | C82: =C78*(C80+Assumptions!$B$10) -> 7112.7022 | D82: =D78*(D80+Assumptions!$B$10) -> 6030.4383 | E82: =E78*(E80+Assumptions!$B$10) -> 4915.3812 | F82: =F78*(F80+Assumptions!$B$10) -> 4117.0995 | G82: =G78*(G80+Assumptions!$B$10) -> 3535.2939
A83: Net income ($mn) | B83: 5938 | C83: =C82*(1-Assumptions!$B$11) -> 5298.9631 | D83: =D82*(1-Assumptions!$B$11) -> 4492.6766 | E83: =E82*(1-Assumptions!$B$11) -> 3661.959 | F83: =F82*(1-Assumptions!$B$11) -> 3067.2391 | G83: =G82*(1-Assumptions!$B$11) -> 2633.7939
A84: net margin | B84: 0.198 | C84: =C83/C78 -> 0.186995 | D84: =D83/D78 -> 0.17582 | E84: =E83/E78 -> 0.16241 | F84: =F83/F78 -> 0.15198 | G84: =G83/G78 -> 0.142295
A85: ₹ / US$ | B85: 88.956591 | C85: =B85*(1+Assumptions!$B$9) -> 90.735723 | D85: =C85*(1+Assumptions!$B$9) -> 92.550438 | E85: =D85*(1+Assumptions!$B$9) -> 94.401446 | F85: =E85*(1+Assumptions!$B$9) -> 96.289475 | G85: =F85*(1+Assumptions!$B$9) -> 98.215265
A86: Revenue (₹ crore) | B86: 267021 | C86: =C78*C85/10 -> 257121.98 | D86: =D78*D85/10 -> 236491.4 | E86: =E78*E85/10 -> 212852.8 | F86: =F78*F85/10 -> 194330.07 | G86: =G78*G85/10 -> 181790.48
A87: Net income (₹ crore) | B87: 49454 | C87: =C83*C85/10 -> 48080.525 | D87: =D83*D85/10 -> 41579.918 | E87: =E83*E85/10 -> 34569.423 | F87: =F83*F85/10 -> 29534.285 | G87: =G83*G85/10 -> 25867.877
A88: Free cash flow (₹ crore) | B88: 42983 | C88: =C87*Assumptions!B91 -> 36060.394 | D88: =D87*Assumptions!C91 -> 27442.746 | E88: =E87*Assumptions!D91 -> 23507.207 | F88: =F87*Assumptions!E91 -> 21855.371 | G88: =G87*Assumptions!F91 -> 20694.301
A89: Total dividend (₹ crore) | B89: 39571 | C89: =C88*Assumptions!B92 -> 34257.374 | D89: =D88*Assumptions!C92 -> 24698.471 | E89: =E88*Assumptions!D92 -> 19981.126 | F89: =F88*Assumptions!E92 -> 18577.065 | G89: =G88*Assumptions!F92 -> 17590.156
A90: Dividend per share (₹) | B90: 110 | C90: =C89/Assumptions!$B$13 -> 94.685943 | D90: =D89/Assumptions!$B$13 -> 68.265537 | E90: =E89/Assumptions!$B$13 -> 55.226993 | F90: =F89/Assumptions!$B$13 -> 51.346227 | G90: =G89/Assumptions!$B$13 -> 48.618453
A91: Dividend to Tata Sons (₹ crore) | B91: 28291 | C91: =C89*Assumptions!$B$12 -> 24576.24 | D91: =D89*Assumptions!$B$12 -> 17718.683 | E91: =E89*Assumptions!$B$12 -> 14334.46 | F91: =F89*Assumptions!$B$12 -> 13327.186 | G91: =G89*Assumptions!$B$12 -> 12619.178
A92: Revenue per employee ($) | B92: 51353 | C92: =B92*(1+Assumptions!$B$93) -> 52123.295 | D92: =C92*(1+Assumptions!$B$93) -> 52905.144 | E92: =D92*(1+Assumptions!$B$93) -> 53698.722 | F92: =E92*(1+Assumptions!$B$93) -> 54504.202 | G92: =F92*(1+Assumptions!$B$93) -> 55321.765
A93: Closing headcount | B93: 584519 | C93: =C78*1000000/C92 -> 543662.08 | D93: =D78*1000000/D92 -> 482990.93 | E93: =E78*1000000/E92 -> 419891.19 | F93: =F78*1000000/F92 -> 370280.81 | G93: =G78*1000000/G92 -> 334577.03
A94: change vs FY26 | C94: =C93-$B$93 -> -40856.923 | D94: =D93-$B$93 -> -101528.07 | E94: =E93-$B$93 -> -164627.81 | F94: =F93-$B$93 -> -214238.19 | G94: =G93-$B$93 -> -249941.97
A96: FY26–FY31 revenue CAGR | C96: =(G78/B78)^(1/5)-1 -> -0.092169074
A97: Cumulative dividend to Tata Sons, FY27–FY31 (₹ crore) | C97: =SUM(C91:G91) -> 82575.748
A100: Probability-weighted expected case
B101: FY26A | C101: FY27 | D101: FY28 | E101: FY29 | F101: FY30 | G101: FY31
A102: Revenue ($mn) | B102: =B6*Assumptions!$I$28+B30*Assumptions!$I$45+B54*Assumptions!$I$62+B78*Assumptions!$I$79 -> 30017 | C102: =C6*Assumptions!$I$28+C30*Assumptions!$I$45+C54*Assumptions!$I$62+C78*Assumptions!$I$79 -> 30470.008 | D102: =D6*Assumptions!$I$28+D30*Assumptions!$I$45+D54*Assumptions!$I$62+D78*Assumptions!$I$79 -> 30671.705 | E102: =E6*Assumptions!$I$28+E30*Assumptions!$I$45+E54*Assumptions!$I$62+E78*Assumptions!$I$79 -> 30842.029 | F102: =F6*Assumptions!$I$28+F30*Assumptions!$I$45+F54*Assumptions!$I$62+F78*Assumptions!$I$79 -> 31271.94 | G102: =G6*Assumptions!$I$28+G30*Assumptions!$I$45+G54*Assumptions!$I$62+G78*Assumptions!$I$79 -> 31911.729
A103: Net income ($mn) | B103: =B11*Assumptions!$I$28+B35*Assumptions!$I$45+B59*Assumptions!$I$62+B83*Assumptions!$I$79 -> 5938 | C103: =C11*Assumptions!$I$28+C35*Assumptions!$I$45+C59*Assumptions!$I$62+C83*Assumptions!$I$79 -> 5841.5739 | D103: =D11*Assumptions!$I$28+D35*Assumptions!$I$45+D59*Assumptions!$I$62+D83*Assumptions!$I$79 -> 5872.1287 | E103: =E11*Assumptions!$I$28+E35*Assumptions!$I$45+E59*Assumptions!$I$62+E83*Assumptions!$I$79 -> 5908.9695 | F103: =F11*Assumptions!$I$28+F35*Assumptions!$I$45+F59*Assumptions!$I$62+F83*Assumptions!$I$79 -> 6005.325 | G103: =G11*Assumptions!$I$28+G35*Assumptions!$I$45+G59*Assumptions!$I$62+G83*Assumptions!$I$79 -> 6153.6483
A104: Total dividend (₹ crore) | B104: =B17*Assumptions!$I$28+B41*Assumptions!$I$45+B65*Assumptions!$I$62+B89*Assumptions!$I$79 -> 39571 | C104: =C17*Assumptions!$I$28+C41*Assumptions!$I$45+C65*Assumptions!$I$62+C89*Assumptions!$I$79 -> 39092.435 | D104: =D17*Assumptions!$I$28+D41*Assumptions!$I$45+D65*Assumptions!$I$62+D89*Assumptions!$I$79 -> 36991.99 | E104: =E17*Assumptions!$I$28+E41*Assumptions!$I$45+E65*Assumptions!$I$62+E89*Assumptions!$I$79 -> 38787.946 | F104: =F17*Assumptions!$I$28+F41*Assumptions!$I$45+F65*Assumptions!$I$62+F89*Assumptions!$I$79 -> 42590.4 | G104: =G17*Assumptions!$I$28+G41*Assumptions!$I$45+G65*Assumptions!$I$62+G89*Assumptions!$I$79 -> 46682.516
A105: Dividend to Tata Sons (₹ crore) | B105: =B19*Assumptions!$I$28+B43*Assumptions!$I$45+B67*Assumptions!$I$62+B91*Assumptions!$I$79 -> 28291 | C105: =C19*Assumptions!$I$28+C43*Assumptions!$I$45+C67*Assumptions!$I$62+C91*Assumptions!$I$79 -> 28044.913 | D105: =D19*Assumptions!$I$28+D43*Assumptions!$I$45+D67*Assumptions!$I$62+D91*Assumptions!$I$79 -> 26538.054 | E105: =E19*Assumptions!$I$28+E43*Assumptions!$I$45+E67*Assumptions!$I$62+E91*Assumptions!$I$79 -> 27826.472 | F105: =F19*Assumptions!$I$28+F43*Assumptions!$I$45+F67*Assumptions!$I$62+F91*Assumptions!$I$79 -> 30554.353 | G105: =G19*Assumptions!$I$28+G43*Assumptions!$I$45+G67*Assumptions!$I$62+G91*Assumptions!$I$79 -> 33490.037
A106: Closing headcount | B106: =B21*Assumptions!$I$28+B45*Assumptions!$I$45+B69*Assumptions!$I$62+B93*Assumptions!$I$79 -> 584519 | C106: =C21*Assumptions!$I$28+C45*Assumptions!$I$45+C69*Assumptions!$I$62+C93*Assumptions!$I$79 -> 572781.63 | D106: =D21*Assumptions!$I$28+D45*Assumptions!$I$45+D69*Assumptions!$I$62+D93*Assumptions!$I$79 -> 555927.05 | E106: =E21*Assumptions!$I$28+E45*Assumptions!$I$45+E69*Assumptions!$I$62+E93*Assumptions!$I$79 -> 538260.28 | F106: =F21*Assumptions!$I$28+F45*Assumptions!$I$45+F69*Assumptions!$I$62+F93*Assumptions!$I$79 -> 524966.88 | G106: =G21*Assumptions!$I$28+G45*Assumptions!$I$45+G69*Assumptions!$I$62+G93*Assumptions!$I$79 -> 514912.85
A108: Expected FY26–FY31 revenue CAGR | C108: =(G102/B102)^(1/5)-1 -> 0.012317185

Sheet Tata Sons Bridge
A1: Tata Sons — parent-level cash bridge (₹ crore)
A2: Does the TCS dividend still fund the group's strategic bets? Capital deployment is held constant across scenarios: the commitments do not shrink because TCS slows.
A4: Bull — AI Dividend
B5: FY26A | C5: FY27 | D5: FY28 | E5: FY29 | F5: FY30 | G5: FY31
A6: Dividend from TCS | B6: 28291 | C6: ='Scenario Output'!C19 -> 30543.662 | D6: ='Scenario Output'!D19 -> 33106.925 | E6: ='Scenario Output'!E19 -> 39899.824 | F6: ='Scenario Output'!F19 -> 48056.707 | G6: ='Scenario Output'!G19 -> 56618.347
A7: Dividend from other listed holdings | B7: 4237 | C7: =B7*(1+Assumptions!$B$98) -> 4618.33 | D7: =C7*(1+Assumptions!$B$98) -> 5033.9797 | E7: =D7*(1+Assumptions!$B$98) -> 5487.0379 | F7: =E7*(1+Assumptions!$B$98) -> 5980.8713 | G7: =F7*(1+Assumptions!$B$98) -> 6519.1497
A8: Total dividend inflow | B8: =B6+B7 -> 32528 | C8: =C6+C7 -> 35161.992 | D8: =D6+D7 -> 38140.905 | E8: =E6+E7 -> 45386.862 | F8: =F6+F7 -> 54037.578 | G8: =G6+G7 -> 63137.497
A9: Parent opex, interest and tax | B9: 6984 | C9: =B9*(1+Assumptions!$B$100) -> 7403.04 | D9: =C9*(1+Assumptions!$B$100) -> 7847.2224 | E9: =D9*(1+Assumptions!$B$100) -> 8318.0557 | F9: =E9*(1+Assumptions!$B$100) -> 8817.1391 | G9: =F9*(1+Assumptions!$B$100) -> 9346.1674
A10: Equity deployment into strategic bets | B10: 15956 | C10: =Assumptions!B104 -> 20000 | D10: =Assumptions!C104 -> 24000 | E10: =Assumptions!D104 -> 26000 | F10: =Assumptions!E104 -> 27000 | G10: =Assumptions!F104 -> 28000
A11: Surplus / (deficit) | B11: =B8-B9-B10 -> 9588 | C11: =C8-C9-C10 -> 7758.952 | D11: =D8-D9-D10 -> 6293.6822 | E11: =E8-E9-E10 -> 11068.806 | F11: =F8-F9-F10 -> 18220.439 | G11: =G8-G9-G10 -> 25791.329
A12: Cumulative net cash | B12: 21841 | C12: =B12+C11 -> 29599.952 | D12: =C12+D11 -> 35893.634 | E12: =D12+E11 -> 46962.44 | F12: =E12+F11 -> 65182.879 | G12: =F12+G11 -> 90974.208
A13: TCS as % of dividend inflow | B13: =B6/B8 -> 0.86974299 | C13: =C6/C8 -> 0.86865562 | D13: =D6/D8 -> 0.86801625 | E13: =E6/E8 -> 0.87910515 | F13: =F6/F8 -> 0.88932015 | G13: =G6/G8 -> 0.89674678
A14: Dividend cover of capital call (×) | B14: =B8/B10 -> 2.0386062 | C14: =C8/C10 -> 1.7580996 | D14: =D8/D10 -> 1.5892044 | E14: =E8/E10 -> 1.7456485 | F14: =F8/F10 -> 2.0013918 | G14: =G8/G10 -> 2.2549106
A16: Cumulative surplus / (deficit) FY27–FY31 | C16: =SUM(C11:G11) -> 69133.208
A19: Base — Managed Transition
B20: FY26A | C20: FY27 | D20: FY28 | E20: FY29 | F20: FY30 | G20: FY31
A21: Dividend from TCS | B21: 28291 | C21: ='Scenario Output'!C43 -> 29108.392 | D21: ='Scenario Output'!D43 -> 29586.085 | E21: ='Scenario Output'!E43 -> 32216.19 | F21: ='Scenario Output'!F43 -> 36152.482 | G21: ='Scenario Output'!G43 -> 40073.796
A22: Dividend from other listed holdings | B22: 4237 | C22: =B22*(1+Assumptions!$B$98) -> 4618.33 | D22: =C22*(1+Assumptions!$B$98) -> 5033.9797 | E22: =D22*(1+Assumptions!$B$98) -> 5487.0379 | F22: =E22*(1+Assumptions!$B$98) -> 5980.8713 | G22: =F22*(1+Assumptions!$B$98) -> 6519.1497
A23: Total dividend inflow | B23: =B21+B22 -> 32528 | C23: =C21+C22 -> 33726.722 | D23: =D21+D22 -> 34620.065 | E23: =E21+E22 -> 37703.228 | F23: =F21+F22 -> 42133.354 | G23: =G21+G22 -> 46592.945
A24: Parent opex, interest and tax | B24: 6984 | C24: =B24*(1+Assumptions!$B$100) -> 7403.04 | D24: =C24*(1+Assumptions!$B$100) -> 7847.2224 | E24: =D24*(1+Assumptions!$B$100) -> 8318.0557 | F24: =E24*(1+Assumptions!$B$100) -> 8817.1391 | G24: =F24*(1+Assumptions!$B$100) -> 9346.1674
A25: Equity deployment into strategic bets | B25: 15956 | C25: =Assumptions!B104 -> 20000 | D25: =Assumptions!C104 -> 24000 | E25: =Assumptions!D104 -> 26000 | F25: =Assumptions!E104 -> 27000 | G25: =Assumptions!F104 -> 28000
A26: Surplus / (deficit) | B26: =B23-B24-B25 -> 9588 | C26: =C23-C24-C25 -> 6323.6819 | D26: =D23-D24-D25 -> 2772.8423 | E26: =E23-E24-E25 -> 3385.1721 | F26: =F23-F24-F25 -> 6316.2144 | G26: =G23-G24-G25 -> 9246.778
A27: Cumulative net cash | B27: 21841 | C27: =B27+C26 -> 28164.682 | D27: =C27+D26 -> 30937.524 | E27: =D27+E26 -> 34322.696 | F27: =E27+F26 -> 40638.911 | G27: =F27+G26 -> 49885.689
A28: TCS as % of dividend inflow | B28: =B21/B23 -> 0.86974299 | C28: =C21/C23 -> 0.86306615 | D28: =D21/D23 -> 0.85459358 | E28: =E21/E23 -> 0.85446769 | F28: =F21/F23 -> 0.85804901 | G28: =G21/G23 -> 0.8600829
A29: Dividend cover of capital call (×) | B29: =B23/B25 -> 2.0386062 | C29: =C23/C25 -> 1.6863361 | D29: =D23/D25 -> 1.4425027 | E29: =E23/E25 -> 1.4501241 | F29: =F23/F25 -> 1.5604946 | G29: =G23/G25 -> 1.6640338
A31: Cumulative surplus / (deficit) FY27–FY31 | C31: =SUM(C26:G26) -> 28044.689
A34: Bear — Slow Bleed
B35: FY26A | C35: FY27 | D35: FY28 | E35: FY29 | F35: FY30 | G35: FY31
A36: Dividend from TCS | B36: 28291 | C36: ='Scenario Output'!C67 -> 27111.903 | D36: ='Scenario Output'!D67 -> 23599.262 | E36: ='Scenario Output'!E67 -> 22682.846 | F36: ='Scenario Output'!F67 -> 22952.588 | G36: ='Scenario Output'!G67 -> 23582.966
A37: Dividend from other listed holdings | B37: 4237 | C37: =B37*(1+Assumptions!$B$98) -> 4618.33 | D37: =C37*(1+Assumptions!$B$98) -> 5033.9797 | E37: =D37*(1+Assumptions!$B$98) -> 5487.0379 | F37: =E37*(1+Assumptions!$B$98) -> 5980.8713 | G37: =F37*(1+Assumptions!$B$98) -> 6519.1497
A38: Total dividend inflow | B38: =B36+B37 -> 32528 | C38: =C36+C37 -> 31730.233 | D38: =D36+D37 -> 28633.242 | E38: =E36+E37 -> 28169.884 | F38: =F36+F37 -> 28933.459 | G38: =G36+G37 -> 30102.116
A39: Parent opex, interest and tax | B39: 6984 | C39: =B39*(1+Assumptions!$B$100) -> 7403.04 | D39: =C39*(1+Assumptions!$B$100) -> 7847.2224 | E39: =D39*(1+Assumptions!$B$100) -> 8318.0557 | F39: =E39*(1+Assumptions!$B$100) -> 8817.1391 | G39: =F39*(1+Assumptions!$B$100) -> 9346.1674
A40: Equity deployment into strategic bets | B40: 15956 | C40: =Assumptions!B104 -> 20000 | D40: =Assumptions!C104 -> 24000 | E40: =Assumptions!D104 -> 26000 | F40: =Assumptions!E104 -> 27000 | G40: =Assumptions!F104 -> 28000
A41: Surplus / (deficit) | B41: =B38-B39-B40 -> 9588 | C41: =C38-C39-C40 -> 4327.1933 | D41: =D38-D39-D40 -> -3213.9807 | E41: =E38-E39-E40 -> -6148.1719 | F41: =F38-F39-F40 -> -6883.6798 | G41: =G38-G39-G40 -> -7244.0514
A42: Cumulative net cash | B42: 21841 | C42: =B42+C41 -> 26168.193 | D42: =C42+D41 -> 22954.213 | E42: =D42+E41 -> 16806.041 | F42: =E42+F41 -> 9922.3608 | G42: =F42+G41 -> 2678.3094
A43: TCS as % of dividend inflow | B43: =B36/B38 -> 0.86974299 | C43: =C36/C38 -> 0.85445017 | D43: =D36/D38 -> 0.82419107 | E43: =E36/E38 -> 0.80521617 | F43: =F36/F38 -> 0.79328876 | G43: =G36/G38 -> 0.78343218
A44: Dividend cover of capital call (×) | B44: =B38/B40 -> 2.0386062 | C44: =C38/C40 -> 1.5865117 | D44: =D38/D40 -> 1.1930517 | E44: =E38/E40 -> 1.0834571 | F44: =F38/F40 -> 1.0716096 | G44: =G38/G40 -> 1.0750756
A46: Cumulative surplus / (deficit) FY27–FY31 | C46: =SUM(C41:G41) -> -19162.691
A49: Severe — Structural Break
B50: FY26A | C50: FY27 | D50: FY28 | E50: FY29 | F50: FY30 | G50: FY31
A51: Dividend from TCS | B51: 28291 | C51: ='Scenario Output'!C91 -> 24576.24 | D51: ='Scenario Output'!D91 -> 17718.683 | E51: ='Scenario Output'!E91 -> 14334.46 | F51: ='Scenario Output'!F91 -> 13327.186 | G51: ='Scenario Output'!G91 -> 12619.178
A52: Dividend from other listed holdings | B52: 4237 | C52: =B52*(1+Assumptions!$B$98) -> 4618.33 | D52: =C52*(1+Assumptions!$B$98) -> 5033.9797 | E52: =D52*(1+Assumptions!$B$98) -> 5487.0379 | F52: =E52*(1+Assumptions!$B$98) -> 5980.8713 | G52: =F52*(1+Assumptions!$B$98) -> 6519.1497
A53: Total dividend inflow | B53: =B51+B52 -> 32528 | C53: =C51+C52 -> 29194.57 | D53: =D51+D52 -> 22752.663 | E53: =E51+E52 -> 19821.498 | F53: =F51+F52 -> 19308.058 | G53: =G51+G52 -> 19138.328
A54: Parent opex, interest and tax | B54: 6984 | C54: =B54*(1+Assumptions!$B$100) -> 7403.04 | D54: =C54*(1+Assumptions!$B$100) -> 7847.2224 | E54: =D54*(1+Assumptions!$B$100) -> 8318.0557 | F54: =E54*(1+Assumptions!$B$100) -> 8817.1391 | G54: =F54*(1+Assumptions!$B$100) -> 9346.1674
A55: Equity deployment into strategic bets | B55: 15956 | C55: =Assumptions!B104 -> 20000 | D55: =Assumptions!C104 -> 24000 | E55: =Assumptions!D104 -> 26000 | F55: =Assumptions!E104 -> 27000 | G55: =Assumptions!F104 -> 28000
A56: Surplus / (deficit) | B56: =B53-B54-B55 -> 9588 | C56: =C53-C54-C55 -> 1791.5301 | D56: =D53-D54-D55 -> -9094.5593 | E56: =E53-E54-E55 -> -14496.558 | F56: =F53-F54-F55 -> -16509.081 | G56: =G53-G54-G55 -> -18207.84
A57: Cumulative net cash | B57: 21841 | C57: =B57+C56 -> 23632.53 | D57: =C57+D56 -> 14537.971 | E57: =D57+E56 -> 41.412869 | F57: =E57+F56 -> -16467.668 | G57: =F57+G56 -> -34675.508
A58: TCS as % of dividend inflow | B58: =B51/B53 -> 0.86974299 | C58: =C51/C53 -> 0.8418086 | D58: =D51/D53 -> 0.77875207 | E58: =E51/E53 -> 0.72317744 | F58: =F51/F53 -> 0.69023962 | G58: =G51/G53 -> 0.65936681
A59: Dividend cover of capital call (×) | B59: =B53/B55 -> 2.0386062 | C59: =C53/C55 -> 1.4597285 | D59: =D53/D55 -> 0.94802763 | E59: =E53/E55 -> 0.7623653 | F59: =F53/F55 -> 0.71511325 | G59: =G53/G55 -> 0.68351171
A61: Cumulative surplus / (deficit) FY27–FY31 | C61: =SUM(C56:G56) -> -56516.508

Sheet Sensitivity
A1: Sensitivity — FY31 dividend to Tata Sons (₹ crore)
A2: Rows: FY26–FY31 revenue CAGR (constant currency). Columns: FY31 operating margin.
A4: Fixed inputs for this grid
A5: FY26 revenue ($mn) | B5: =Assumptions!B5 -> 30017
A6: FY31 ₹/US$ | B6: =Assumptions!B8*(1+Assumptions!B9)^5 -> 98.219028
A7: Free cash flow / net income | B7: 0.82
A8: Dividend as % of free cash flow | B8: 0.92
A10: FY31 dividend to Tata Sons (₹ crore)
A11: Revenue CAGR \ FY31 margin | B11: 0.175 | C11: 0.19 | D11: 0.205 | E11: 0.22 | F11: 0.235 | G11: 0.25 | H11: 0.265
A12: -0.09 | B12: =$B$5*(1+$A12)^5*(B$11+Assumptions!$B$10)*(1-Assumptions!$B$11)*$B$6/10*$B$7*$B$8*Assumptions!$B$12 -> 14168.458 | C12: =$B$5*(1+$A12)^5*(C$11+Assumptions!$B$10)*(1-Assumptions!$B$11)*$B$6/10*$B$7*$B$8*Assumptions!$B$12 -> 15281.164 | D12: =$B$5*(1+$A12)^5*(D$11+Assumptions!$B$10)*(1-Assumptions!$B$11)*$B$6/10*$B$7*$B$8*Assumptions!$B$12 -> 16393.87 | E12: =$B$5*(1+$A12)^5*(E$11+Assumptions!$B$10)*(1-Assumptions!$B$11)*$B$6/10*$B$7*$B$8*Assumptions!$B$12 -> 17506.576 | F12: =$B$5*(1+$A12)^5*(F$11+Assumptions!$B$10)*(1-Assumptions!$B$11)*$B$6/10*$B$7*$B$8*Assumptions!$B$12 -> 18619.282 | G12: =$B$5*(1+$A12)^5*(G$11+Assumptions!$B$10)*(1-Assumptions!$B$11)*$B$6/10*$B$7*$B$8*Assumptions!$B$12 -> 19731.988 | H12: =$B$5*(1+$A12)^5*(H$11+Assumptions!$B$10)*(1-Assumptions!$B$11)*$B$6/10*$B$7*$B$8*Assumptions!$B$12 -> 20844.694
A13: -0.06 | B13: =$B$5*(1+$A13)^5*(B$11+Assumptions!$B$10)*(1-Assumptions!$B$11)*$B$6/10*$B$7*$B$8*Assumptions!$B$12 -> 16663.065 | C13: =$B$5*(1+$A13)^5*(C$11+Assumptions!$B$10)*(1-Assumptions!$B$11)*$B$6/10*$B$7*$B$8*Assumptions!$B$12 -> 17971.682 | D13: =$B$5*(1+$A13)^5*(D$11+Assumptions!$B$10)*(1-Assumptions!$B$11)*$B$6/10*$B$7*$B$8*Assumptions!$B$12 -> 19280.3 | E13: =$B$5*(1+$A13)^5*(E$11+Assumptions!$B$10)*(1-Assumptions!$B$11)*$B$6/10*$B$7*$B$8*Assumptions!$B$12 -> 20588.918 | F13: =$B$5*(1+$A13)^5*(F$11+Assumptions!$B$10)*(1-Assumptions!$B$11)*$B$6/10*$B$7*$B$8*Assumptions!$B$12 -> 21897.535 | G13: =$B$5*(1+$A13)^5*(G$11+Assumptions!$B$10)*(1-Assumptions!$B$11)*$B$6/10*$B$7*$B$8*Assumptions!$B$12 -> 23206.153 | H13: =$B$5*(1+$A13)^5*(H$11+Assumptions!$B$10)*(1-Assumptions!$B$11)*$B$6/10*$B$7*$B$8*Assumptions!$B$12 -> 24514.77
A14: -0.03 | B14: =$B$5*(1+$A14)^5*(B$11+Assumptions!$B$10)*(1-Assumptions!$B$11)*$B$6/10*$B$7*$B$8*Assumptions!$B$12 -> 19497.291 | C14: =$B$5*(1+$A14)^5*(C$11+Assumptions!$B$10)*(1-Assumptions!$B$11)*$B$6/10*$B$7*$B$8*Assumptions!$B$12 -> 21028.492 | D14: =$B$5*(1+$A14)^5*(D$11+Assumptions!$B$10)*(1-Assumptions!$B$11)*$B$6/10*$B$7*$B$8*Assumptions!$B$12 -> 22559.693 | E14: =$B$5*(1+$A14)^5*(E$11+Assumptions!$B$10)*(1-Assumptions!$B$11)*$B$6/10*$B$7*$B$8*Assumptions!$B$12 -> 24090.894 | F14: =$B$5*(1+$A14)^5*(F$11+Assumptions!$B$10)*(1-Assumptions!$B$11)*$B$6/10*$B$7*$B$8*Assumptions!$B$12 -> 25622.095 | G14: =$B$5*(1+$A14)^5*(G$11+Assumptions!$B$10)*(1-Assumptions!$B$11)*$B$6/10*$B$7*$B$8*Assumptions!$B$12 -> 27153.296 | H14: =$B$5*(1+$A14)^5*(H$11+Assumptions!$B$10)*(1-Assumptions!$B$11)*$B$6/10*$B$7*$B$8*Assumptions!$B$12 -> 28684.497
A15: 0 | B15: =$B$5*(1+$A15)^5*(B$11+Assumptions!$B$10)*(1-Assumptions!$B$11)*$B$6/10*$B$7*$B$8*Assumptions!$B$12 -> 22704.692 | C15: =$B$5*(1+$A15)^5*(C$11+Assumptions!$B$10)*(1-Assumptions!$B$11)*$B$6/10*$B$7*$B$8*Assumptions!$B$12 -> 24487.783 | D15: =$B$5*(1+$A15)^5*(D$11+Assumptions!$B$10)*(1-Assumptions!$B$11)*$B$6/10*$B$7*$B$8*Assumptions!$B$12 -> 26270.874 | E15: =$B$5*(1+$A15)^5*(E$11+Assumptions!$B$10)*(1-Assumptions!$B$11)*$B$6/10*$B$7*$B$8*Assumptions!$B$12 -> 28053.965 | F15: =$B$5*(1+$A15)^5*(F$11+Assumptions!$B$10)*(1-Assumptions!$B$11)*$B$6/10*$B$7*$B$8*Assumptions!$B$12 -> 29837.056 | G15: =$B$5*(1+$A15)^5*(G$11+Assumptions!$B$10)*(1-Assumptions!$B$11)*$B$6/10*$B$7*$B$8*Assumptions!$B$12 -> 31620.147 | H15: =$B$5*(1+$A15)^5*(H$11+Assumptions!$B$10)*(1-Assumptions!$B$11)*$B$6/10*$B$7*$B$8*Assumptions!$B$12 -> 33403.238
A16: 0.02 | B16: =$B$5*(1+$A16)^5*(B$11+Assumptions!$B$10)*(1-Assumptions!$B$11)*$B$6/10*$B$7*$B$8*Assumptions!$B$12 -> 25067.814 | C16: =$B$5*(1+$A16)^5*(C$11+Assumptions!$B$10)*(1-Assumptions!$B$11)*$B$6/10*$B$7*$B$8*Assumptions!$B$12 -> 27036.491 | D16: =$B$5*(1+$A16)^5*(D$11+Assumptions!$B$10)*(1-Assumptions!$B$11)*$B$6/10*$B$7*$B$8*Assumptions!$B$12 -> 29005.167 | E16: =$B$5*(1+$A16)^5*(E$11+Assumptions!$B$10)*(1-Assumptions!$B$11)*$B$6/10*$B$7*$B$8*Assumptions!$B$12 -> 30973.844 | F16: =$B$5*(1+$A16)^5*(F$11+Assumptions!$B$10)*(1-Assumptions!$B$11)*$B$6/10*$B$7*$B$8*Assumptions!$B$12 -> 32942.52 | G16: =$B$5*(1+$A16)^5*(G$11+Assumptions!$B$10)*(1-Assumptions!$B$11)*$B$6/10*$B$7*$B$8*Assumptions!$B$12 -> 34911.197 | H16: =$B$5*(1+$A16)^5*(H$11+Assumptions!$B$10)*(1-Assumptions!$B$11)*$B$6/10*$B$7*$B$8*Assumptions!$B$12 -> 36879.873
A17: 0.04 | B17: =$B$5*(1+$A17)^5*(B$11+Assumptions!$B$10)*(1-Assumptions!$B$11)*$B$6/10*$B$7*$B$8*Assumptions!$B$12 -> 27623.729 | C17: =$B$5*(1+$A17)^5*(C$11+Assumptions!$B$10)*(1-Assumptions!$B$11)*$B$6/10*$B$7*$B$8*Assumptions!$B$12 -> 29793.132 | D17: =$B$5*(1+$A17)^5*(D$11+Assumptions!$B$10)*(1-Assumptions!$B$11)*$B$6/10*$B$7*$B$8*Assumptions!$B$12 -> 31962.535 | E17: =$B$5*(1+$A17)^5*(E$11+Assumptions!$B$10)*(1-Assumptions!$B$11)*$B$6/10*$B$7*$B$8*Assumptions!$B$12 -> 34131.938 | F17: =$B$5*(1+$A17)^5*(F$11+Assumptions!$B$10)*(1-Assumptions!$B$11)*$B$6/10*$B$7*$B$8*Assumptions!$B$12 -> 36301.34 | G17: =$B$5*(1+$A17)^5*(G$11+Assumptions!$B$10)*(1-Assumptions!$B$11)*$B$6/10*$B$7*$B$8*Assumptions!$B$12 -> 38470.743 | H17: =$B$5*(1+$A17)^5*(H$11+Assumptions!$B$10)*(1-Assumptions!$B$11)*$B$6/10*$B$7*$B$8*Assumptions!$B$12 -> 40640.146
A18: 0.06 | B18: =$B$5*(1+$A18)^5*(B$11+Assumptions!$B$10)*(1-Assumptions!$B$11)*$B$6/10*$B$7*$B$8*Assumptions!$B$12 -> 30383.999 | C18: =$B$5*(1+$A18)^5*(C$11+Assumptions!$B$10)*(1-Assumptions!$B$11)*$B$6/10*$B$7*$B$8*Assumptions!$B$12 -> 32770.177 | D18: =$B$5*(1+$A18)^5*(D$11+Assumptions!$B$10)*(1-Assumptions!$B$11)*$B$6/10*$B$7*$B$8*Assumptions!$B$12 -> 35156.355 | E18: =$B$5*(1+$A18)^5*(E$11+Assumptions!$B$10)*(1-Assumptions!$B$11)*$B$6/10*$B$7*$B$8*Assumptions!$B$12 -> 37542.533 | F18: =$B$5*(1+$A18)^5*(F$11+Assumptions!$B$10)*(1-Assumptions!$B$11)*$B$6/10*$B$7*$B$8*Assumptions!$B$12 -> 39928.711 | G18: =$B$5*(1+$A18)^5*(G$11+Assumptions!$B$10)*(1-Assumptions!$B$11)*$B$6/10*$B$7*$B$8*Assumptions!$B$12 -> 42314.889 | H18: =$B$5*(1+$A18)^5*(H$11+Assumptions!$B$10)*(1-Assumptions!$B$11)*$B$6/10*$B$7*$B$8*Assumptions!$B$12 -> 44701.067
A19: 0.08 | B19: =$B$5*(1+$A19)^5*(B$11+Assumptions!$B$10)*(1-Assumptions!$B$11)*$B$6/10*$B$7*$B$8*Assumptions!$B$12 -> 33360.641 | C19: =$B$5*(1+$A19)^5*(C$11+Assumptions!$B$10)*(1-Assumptions!$B$11)*$B$6/10*$B$7*$B$8*Assumptions!$B$12 -> 35980.587 | D19: =$B$5*(1+$A19)^5*(D$11+Assumptions!$B$10)*(1-Assumptions!$B$11)*$B$6/10*$B$7*$B$8*Assumptions!$B$12 -> 38600.532 | E19: =$B$5*(1+$A19)^5*(E$11+Assumptions!$B$10)*(1-Assumptions!$B$11)*$B$6/10*$B$7*$B$8*Assumptions!$B$12 -> 41220.478 | F19: =$B$5*(1+$A19)^5*(F$11+Assumptions!$B$10)*(1-Assumptions!$B$11)*$B$6/10*$B$7*$B$8*Assumptions!$B$12 -> 43840.424 | G19: =$B$5*(1+$A19)^5*(G$11+Assumptions!$B$10)*(1-Assumptions!$B$11)*$B$6/10*$B$7*$B$8*Assumptions!$B$12 -> 46460.369 | H19: =$B$5*(1+$A19)^5*(H$11+Assumptions!$B$10)*(1-Assumptions!$B$11)*$B$6/10*$B$7*$B$8*Assumptions!$B$12 -> 49080.315
A20: 0.1 | B20: =$B$5*(1+$A20)^5*(B$11+Assumptions!$B$10)*(1-Assumptions!$B$11)*$B$6/10*$B$7*$B$8*Assumptions!$B$12 -> 36566.133 | C20: =$B$5*(1+$A20)^5*(C$11+Assumptions!$B$10)*(1-Assumptions!$B$11)*$B$6/10*$B$7*$B$8*Assumptions!$B$12 -> 39437.819 | D20: =$B$5*(1+$A20)^5*(D$11+Assumptions!$B$10)*(1-Assumptions!$B$11)*$B$6/10*$B$7*$B$8*Assumptions!$B$12 -> 42309.505 | E20: =$B$5*(1+$A20)^5*(E$11+Assumptions!$B$10)*(1-Assumptions!$B$11)*$B$6/10*$B$7*$B$8*Assumptions!$B$12 -> 45181.191 | F20: =$B$5*(1+$A20)^5*(F$11+Assumptions!$B$10)*(1-Assumptions!$B$11)*$B$6/10*$B$7*$B$8*Assumptions!$B$12 -> 48052.877 | G20: =$B$5*(1+$A20)^5*(G$11+Assumptions!$B$10)*(1-Assumptions!$B$11)*$B$6/10*$B$7*$B$8*Assumptions!$B$12 -> 50924.562 | H20: =$B$5*(1+$A20)^5*(H$11+Assumptions!$B$10)*(1-Assumptions!$B$11)*$B$6/10*$B$7*$B$8*Assumptions!$B$12 -> 53796.248
A22: Reference: Tata Sons received ₹28,291 crore from TCS in FY26 and ₹32,184 crore in FY25. Cells below ~₹28,000 crore mean the parent's dividend income does not recover to FY26 levels by FY31.
A25: Break-even check
A26: FY31 capital call on Tata Sons (₹ crore) | B26: =Assumptions!F104 -> 28000
A27: Plus parent opex, interest and tax (₹ crore) | B27: =Assumptions!B99*(1+Assumptions!B100)^5 -> 9346.1674
A28: Less non-TCS dividend income (₹ crore) | B28: =-Assumptions!B97*(1+Assumptions!B98)^5 -> -6519.1497
A29: TCS dividend to Tata Sons needed to break even in FY31 | B29: =SUM(B26:B28) -> 30827.018

Sheet Risk Register
A1: Revenue at risk by exposure bucket
A2: Gross revenue at risk = FY26 revenue in the bucket × the share of its work AI can substantially automate by FY31. It is a measure of exposure, not of expected loss: what is actually lost depends on how much of the productivity gain is passed to the client and how far volume expands in response.
A4: Exposure bucket | B4: FY26 weight | C4: FY26 $mn | D4: Automatable share | E4: Gross rev at risk $mn | F4: Severe-case FY31 $mn | G4: Assessment
A5: Application Development & Maintenance (custom) | B5: =Assumptions!B17 -> 0.32 | C5: =Assumptions!C17 -> 9605.44 | D5: =Assumptions!D17 -> 0.55 | E5: =Assumptions!E17 -> 5282.992 | F5: ='Revenue Build'!G48 -> 4920.9778 | G5: Code generation, test automation and agentic L1/L2 support attack the core of this book. Largest single pool and the most exposed.
A6: Enterprise / Package Application Services | B6: =Assumptions!B18 -> 0.13 | C6: =Assumptions!C18 -> 3902.21 | D6: =Assumptions!D18 -> 0.4 | E6: =Assumptions!E18 -> 1560.884 | F6: ='Revenue Build'!G49 -> 2481.1232 | G6: SAP/Oracle/Salesforce migration and rollout. Config work automates; change management, data migration and integration hold value.
A7: Cloud & Infrastructure Managed Services | B7: =Assumptions!B19 -> 0.16 | C7: =Assumptions!C19 -> 4802.72 | D7: =Assumptions!D19 -> 0.5 | E7: =Assumptions!E19 -> 2401.36 | F7: ='Revenue Build'!G50 -> 2884.4593 | G7: AIOps compresses run-cost; offset by AI-infrastructure build, GPU estate operations and the HyperVault adjacency.
A8: Business Process Services | B8: =Assumptions!B20 -> 0.1 | C8: =Assumptions!C20 -> 3001.7 | D8: =Assumptions!D20 -> 0.65 | E8: =Assumptions!E20 -> 1951.105 | F8: ='Revenue Build'!G51 -> 1045.7089 | G8: Most directly substitutable. Agentic workflows displace seat-based delivery; the FTE pricing model is the liability.
A9: Engineering & R&D Services | B9: =Assumptions!B21 -> 0.09 | C9: =Assumptions!C21 -> 2701.53 | D9: =Assumptions!D21 -> 0.25 | E9: =Assumptions!E21 -> 675.3825 | F9: ='Revenue Build'!G52 -> 2109.6361 | G9: Embedded, semiconductor, automotive software. Least substitutable near-term and structurally growing.
A10: Consulting, Data, AI & Cybersecurity | B10: =Assumptions!B22 -> 0.15 | C10: =Assumptions!C22 -> 4502.55 | D10: =Assumptions!D22 -> 0.15 | E10: =Assumptions!E22 -> 675.3825 | F10: ='Revenue Build'!G53 -> 3854.0231 | G10: The growth engine. AI-native demand, data estate rebuild, model governance, security. TCS AI book already ~8.5% of revenue.
A11: Products & Platforms (BaNCS, ignio, iON, ADD) | B11: =Assumptions!B23 -> 0.05 | C11: =Assumptions!C23 -> 1500.85 | D11: =Assumptions!D23 -> 0.1 | E11: =Assumptions!E23 -> 150.085 | F11: ='Revenue Build'!G54 -> 1213.4636 | G11: IP-led, non-linear. AI raises product value rather than deflating it. Strategically under-scaled at ~5% of revenue.
A12: Total | B12: =SUM(B5:B11) -> 1 | C12: =SUM(C5:C11) -> 30017 | E12: =SUM(E5:E11) -> 12697.191 | F12: =SUM(F5:F11) -> 18509.392
A14: Gross revenue at risk as % of FY26 revenue | C14: =E12/C12 -> 0.423
